Workbook
Name A25300000: #REF!

Sheet FORMATO ACTUALIZACIÓN DATOS
A1: SECRETARÍA DE EDUCACIÓN DE BOGOTÁ
A2: OFICINA DE TESORERÍA Y CONTABILIDAD
A4: FORMULARIO DE ACTUALIZACIÓN DE DATOS PARA PERSONAS NATURALES HONORARIOS Y SERVICIOS PERSONALES ART.103 DEL ET
A8: IDENTIFICACIÓN
A10: Número de Identificación Tributaria (NIT): | P10: DV | R10: Tipo de Contribuyente | AC10: Tipo de Documento | AP10: =IF(AA11=1,"Número de Identificación del Contacto","Número de Identificación") -> Número de Identificación
R11: PERSONA NATURAL | AA11: =IFERROR(VLOOKUP(R11,'Validador- Datos'!K16:L18,2,0),"") -> 2 | AN11: =IFERROR(VLOOKUP(AC11,'Validador- Datos'!K1:M14,2,0),"")
A13: =CLEAN(TRIM(A11)) | P13: =+A13-AP13 -> #VALUE! | R13: =IFERROR(IF(AA11=1,1,IF(P13=0,1,0)),0) -> 0 | AA13: =IF(AA11=1,"J",IF(AA11=2,"N","")) -> N | AN13: =IFERROR(VLOOKUP(AN11,'Validador- Datos'!L2:M14,2,0),"") | AP13: =IFERROR(VALUE(CLEAN(TRIM(AP11))),"")
A14: =CONCATENATE(A11,B11,C11,D11,E11,F11,G11,H11,I11,J11,K11,L11,M11,N11) | AP14: =CONCATENATE(AP11,AQ11,AR11,AS11,AT11,AU11,AV11,AW11,AX11,AY11,AZ11,BA11,BB11,BC11)
A15: Primer Apellido | I15: Segundo Apellido | Q15: Primer Nombre | Y15: Otros Nombres | AI15: Nombre Completo
AI16: =CONCATENATE(UPPER(A16)," ",UPPER(I16)," ",UPPER(Q16)," ",UPPER((Y16)))
A18: Es Usted pensionado o ya adquirio los derechos para serlo. | P18: SI | R18: NO | U18: DIRECCIÓN REPORTADA EN EL RUT | AS18: =IF(AC18=0,"",AC18)
A20: País | T20: Departamento (Solo para país Colombia) | AM20: Municipio (Solo para País Colombia)
P21: =IFERROR(VLOOKUP(A21,'Validador- Datos'!T1:U249,2,0),"") | AI21: =IFERROR(VLOOKUP(T21,'Validador- Datos'!W1:X36,2,0),"") | BB21: =IFERROR(VLOOKUP(AM21,'Validador- Datos'!AK1:AL126,2,0),"")
A23: Correo Electrónico | AG23: Teléfono 1 | AQ23: Teléfono 2
A24: cacsa@cascsa.com
AG26: =CLEAN(TRIM(CONCATENATE(AG24,AH24,AI24,AJ24,AK24,AL24,AM24,AN24,AO24,AP24))) | AQ26: =CONCATENATE(AR24,AS24,AT24,AU24,AV24,AW24,AX24,AY24,AZ24,BA24,BB24,BC24)
A28: SISTEMA AUTOMÁTICO DE PAGOS
A30: Banco | Q30: Sucursal | Z30: Tipo Cuenta | AH30: Identificación Titular | AN30: Cuenta Bancaria
M31: =IFERROR(VLOOKUP(A31,bancos[],4,0),"") | AE31: =IFERROR(VLOOKUP(Z31,TIPOCUENTA[],2,0),"") | AH31: =CONCATENATE(A14,"-",P11) -> -
AN32: =TRIM(CONCATENATE(AN31,AO31,AP31,AQ31,AR31,AS31,AT31,AU31,AV31,AW31,AX31,AY31,AZ31,BA31,BB31,BC31))
A36: CLASIFICACIÓN Y RESPONSABILIDADES TRIBUTARIAS
A38: Actividad Económica RUT | X38: Actividad Económica RIT | AU38: Régimen IVA
F39: =IF(A40="","",(IFERROR(VLOOKUP(A40,CIIU[],2,0),"Actividad economica NO existe - por favor verificar"))) | AD39: =IF(X40="","",(IFERROR(VLOOKUP(X40,RIT[],3,0),"Actividad economica NO existe - por favor verificar"))) | AQ39: Tarifa x Mil | BC39: =IFERROR(VLOOKUP(AU39,REGIMEN[],2,0),"")
A40: =CONCATENATE(A39,B39,C39,D39) | X40: =IFERROR(VALUE(CLEAN(TRIM(CONCATENATE(X39,Y39,Z39,AA39,AB39)))),"") | AQ40: =IF(AD39="Actividad economica NO existe o no aplica para el tipo de Contribuyente - por favor verificar","",IF(X40="","",IFERROR(VLOOKUP(X40,'Validador- Datos'!AS2:AV553,4,0),"Actividad economica NO existe - por favor verificar")))
A42: DATOS DEL CONTRATO
A44: No contrato | F44: Año Contrato | K44: Valor Total Contrato | W44: Duración (DÍAS) | AC44: Fecha Acta de Inicio ( aaaa/mm/dd) | AN44: Fecha terminación Contrato ( aaaa/mm/dd) | AY44: Cesión
W46: ='Validador- Datos'!L28
F47: =CONCATENATE(F46,G46,H46,I46)
A49: Valor Pago Mensual según Contrato | N49: CRP 1 | Q49: FECHA CRP 1 aaaa/mm/dd | V49: RP VIGENCIA FUTURA | AC49: CRP 2 | AF49: FECHA CRP 2 aaaa/mm/dd | AN49: CRP 3 | AQ49: FECHA CRP 3 aaaa/mm/dd | AX49: Código Actividad ARL
A52: Área Funcional de la SED | J52: Nombre Interventor Contrato | S52: Cargo Interventor Contrato | Z52: Nombre Operativo | AH52: Identificación Operativo | AP52: Valor del Contrato sin IVA | AW52: =ROUND(IF(AU39="RESPONSABLE IVA",(K46/1.19),IF('Validador- Datos'!BM2>='Validador- Datos'!BL2,'Validador- Datos'!BN2,K46)),0) -> 0
H53: =_xlfn.IFNA(VLOOKUP(A53,ÁREA[#All],2,FALSE),"") | AP53: Valor del IVA del Contrato | AW53: =ROUND(IF(K46<>AW52,AW52*0.19,0),0) -> 0
A58: CERTIFICACIÓN APLICACIÓN RETENCIÓN EN LA FUENTE ARTÍCULOS 383 Y 387 DEL ESTATUTO TRIBUTARIO
A59: FAVOR RESPONDA LAS SIGUIENTES PREGUNTAS:
A61: C1 | C61: 1. ¿Mis ingresos del año gravable 2025 fueron superiores a $ 73´323.600 equivalentes a 1.400 UVT? | AZ61: SI | BB61: NO
A64: C2 | C64: 2. ¿Estoy obligada(o) a declarar Impuesto de Renta para el año 2025? (Ver artículo 592 del Estatuto Tributario) | AZ64: SI | BB64: NO
A67: C3 | C67: 3.¿Pertenezco al Régimen Simple de Tributación -SIMPLE? (LEY 2010 DE 2019) SI LA DIAN NO ME HA CATALOGADO COMO SIMPLE COLOCO LA "X" EN NO | AZ67: SI | BB67: NO
A70: C4 | C70: 4. El trabajador empleará costos y gastos de acuerdo al Decreto 2231 de 2023 | AZ70: SI | BB70: NO
C73: ='Validador- Datos'!BE23 -> REVISE SU INFORMACIÓN TRIBUTARIA
A75: DISMINUCIÓN DE LA BASE DE RETENCIÓN EN LA FUENTE
S76: CERTIFICADOS EXPEDIDOS CON CORTE AL 31 DE DICIEMBRE DE: | AN76: =+'FORMATO DEDUCCIONES'!W16 -> 2025
D79: POR DEPENDIENTES | M79: CRÉDITO HIPOTECARIO | V79: SALUD NO POS | AF79: RECUERDE QUE ESTAS CERTIFICACIONES ESTARAN VIGENTES HASTA EL 14 DE ABRIL DE: | AY79: =+'FORMATO DEDUCCIONES'!W16+2 -> 2027
AF80: UNA VEZ CUMPLIDA ESA FECHA NO TENDRAN NINGUN EFECTO EN LA RETENCIÓN EN LA FUENTE
D82: Cuenta de Ahorro y Fomento a la Construcción (AFC) | R82: SI | U82: NO | AI82: Aporte a Pensiones Voluntarias | AW82: SI | AZ82: NO
D83: Entidad | AI83: Entidad
D84: NIT | AI84: NIT
D85: Valor Mensual | AI85: Valor Mensual
A89: CERTIFICACIÓN DE LOS DATOS
C91: =_xlfn.CONCAT("Yo ",AI16," ",'Validador- Datos'!D69) -> Yo en calidad de contratista manifiesto bajo la gravedad del juramento que la información es veridica y entiendo que soy responsable por los errores u omisiones que genere a la Entidad Contable Pública -Bogotá D.C. por la inexactitud de la misma, y autorizo a la entidad para actualizar la información en las bases de datos, en especial las de la SED, la SHD, la CGN, DIAN y demás entidades de aseguramiento y control del estado. Al firmar este documento, autorizo de manera previa, expresa e informada a la Secretaría de Educación del Distrito para que realice el tratamiento de mis datos personales aquí suministrados. Esta información será utilizada con fines de actualización de información del tercero, conforme a la Ley 1581 de 2012 y a la Política de Tratamiento de Datos disponible en www.educacionbogota.gov.co. Como titular, tengo derecho a conocer, actualizar, rectificar y solicitar la supresión de mis datos, así como a presentar quejas ante la Superintendencia de Industria y Comercio Con la firma del presente formato doy constancia que conozco las condiciones tributarias y obligaciones del mismo derivado del presente contrato.
C95: =IF('Validador- Datos'!D63=FALSE,'Validador- Datos'!D68,"VERIFICAR RESPONSABILIDAD DE IVA POR CUANTIA DEL CONTRATO") -> Por favor verifique la información de : - Número de Identificación Tributaria (NIT) - DV - Tipo de Documento - Número de Identificación - Verificar el Número de Identificación - Primer Apellido - Primer Nombre - Indicar SI es o NO pensionado - Indique la Dirección tal y como aparece en el RUT - País - Departamento - Municipio - Teléfono 1 - Teléfono 2 - Banco - Sucursal - Tipo Cuenta - No Cuenta Bancaria - Actividad Económica RUT - Actividad económica RUT NO existe - por favor verificar - Actividad Económica RIT - Actividad economica RIT NO existe - por favor verificar - Régimen - No Contrato - Año Contrato - Valor Total del Contrato - Valor Pago Mensual según Contrato - Fecha Acta de Inicio - Fecha terminación Contrato - VIGENCIA FUTURA - Cesión - Área Funcional de la SED - Nombre Interventor Contrato - Cargo Interventor Contrato - Nombre Operativo - Identificación Operativo - Codigo ARL - Pregunta C1 - Pregunta C2 - Pregunta C3 - Pregunta C4 - Entidad (AFC) - NIT (AFC) - Valor Mensual (AFC) - Entidad (Pensiones Voluntarias) - NIT (Pensiones Voluntarias) - Valor Mensual (Pensiones Voluntarias) - Número CRP - Fecha del CRP
E101: =IF(AA11=2,AI16,"ERROR")
G102: =_xlfn.CONCAT(AC11,AP13)
F103: =IF(C95="Formulario sin diligenciar","",CONCATENATE("CONTRATO No ",A46," DE ",F47)) -> CONTRATO No DE
BC104: 13-IF-016
BC105: V.1.

Sheet INSTRUCTIVO ACTUALIZACION DATOS
A6: I. OBJETIVO
A7: Establecer las instrucciones para el correcto diligenciamiento del Formato de Actualización de Terceros – Persona Natural, con el fin de registrar y actualizar la información personal, tributaria, bancaria y contractual de los terceros vinculados a la Secretaría de Educación del Distrito, garantizando la confiabilidad de los datos utilizados en los procesos administrativos, financieros y contables de la entidad.
A9: II. ALCANCE
A10: Este instructivo aplica a todas las personas naturales que mantengan o vayan a mantener relación contractual o administrativa con la Secretaría de Educación del Distrito, tales como contratistas, prestadores de servicios que requieran registrarse o actualizar su información en la entidad. Comprende el diligenciamiento del formato, la entrega de los soportes correspondientes y la verificación de la información por parte de las áreas responsables.
A11: III. RESPONSABLE
A13: Contratista (Persona Natural) • Diligenciar completamente el formato de Excel con la información actualizada. •Aportar la documentación soporte requerida • Garantizar la veracidad de la información suministrada. Área Financiera / Tesorería / Grupo de actualizaciones de terceros • Revisar la información registrada. • Validar los datos tributarios y bancarios frente a soportes recibidos • Utilizar la información para incluirla en el sistema Apoteosys para la liquidación de los pagos.
A15: IV. FRECUENCIA
A17: La actualización del formato debe realizarse: • Al inicio del contrato. • Cuando exista cambio en la información tributaria o bancaria. • Cuando la Secretaría de Educación del Distrito lo solicite.
A19: V. INSTRUCCIONES GENERALES DE DILIGENCIAMIENTO
A20: 1. Diligenciar el formato únicamente en las celdas habilitadas (color amarillo). 2. No modificar la estructura del archivo, fórmulas y celdas protegidas. 3. La información registrada debe coincidir con la contenida en el RUT y RIT vigente, así como la certificación bancaria. 4. Verificar que los datos sean correctos antes de remitir el archivo. 5. Adjuntar los soportes requeridos actualizados y la certificación bancaria.
A22: INFORMACIÓN GENERAL DEL TERCERO En esta sección se deben registrar los datos de identificación del tercero objeto de pago: • Número de Identificación Tributaria (NIT): registrar el número de identificación tributaria correspondiente según el RUT. • DV: diligenciar el dígito de verificación indicado en el RUT. • Tipo de Contribuyente: "Persona Natural", se encuentra preestablecido, no registrar información en este campo. • Tipo de Documento: indicar el tipo de identificación del tercero de acuerdo con lista desplegable • Número de Identificación: registrar el número del documento sin puntos ni espacios, sin dígito de verificación del RUT. Datos personales • Primer Apellido • Segundo Apellido • Primer Nombre • Otros Nombres • Nombre Completo: Campo formulado, no registrar información en este campo. Información pensional • Marcar SI o NO en la pregunta: "¿Es usted pensionado o ya adquirió los derechos para serlo?", una vez haya sido validado por la supervisión del contrato.
A23: DIRECCIÓN REGISTRADA EN EL RUT Registrar la información de ubicación según lo reportado en el Registro Único Tributario (RUT): • Dirección • País • Departamento (solo si el país es Colombia) • Municipio (solo si el país es Colombia) Datos de contacto • Correo electrónico • Teléfono 1, dato obligatorio, si no tiene telefono fijo por favor diligenciar 0 • Teléfono 2, número de celular
... A32: El presente formado debe presentarse en formato PDF debidamente FIRMADO por el tercero objeto de actualización de información

Sheet FORMATO DEDUCCIONES
A1: SECRETARÍA DE EDUCACIÓN DE BOGOTÁ
A3: OFICINA DE TESORERÍA Y CONTABILIDAD
A5: FORMULARIO DISMINUCIÓN DE LA BASE DE RETENCIÓN EN LA FUENTE PERSONAS NATURALES OPS
A7: FECHA SOLICITUD
A9: DATOS DEL TERCERO
A11: NOMBRES Y APELLIDOS DEL TERCERO | J11: ='FORMATO ACTUALIZACIÓN DATOS'!AI16
A13: CÉDULA DE CIUDADANÍA No. | G13: ='FORMATO ACTUALIZACIÓN DATOS'!AP11 -> 0 | P13: No CONTRATO | S13: =IF('FORMATO ACTUALIZACIÓN DATOS'!A46,'FORMATO ACTUALIZACIÓN DATOS'!A46," ") | W13: AÑO CONTRATO | Z13: ='FORMATO ACTUALIZACIÓN DATOS'!F47
A15: FECHA EN LA QUE SE DILIGENCIA EL FORMATO: | W15: =TODAY() -> 46204
A16: AÑO FISCAL PARA EL QUE APLICARA EL BENEFICIO : | W16: ='Validador- Datos'!BK12 -> 2025
A18: POR DEPENDIENTES
B20: DATOS DEL DEPENDIENTE
B21: NOMBRES Y APELLIDOS | O21: No DE IDENTIFICACIÓN | U21: EDAD | W21: PARENTESCO
B24: SELECCIONE EL MOTIVO DE LA SOLICITUD:
AC25: =VALUE(LEFT(B25,1)) -> #VALUE!
B28: VALOR MENSUAL | M28: =IFERROR('Validador- Datos'!BM7,"") -> 0
B30: Como soporte se anexa la siguiente documentación:
B31: =IFERROR(VLOOKUP(AC25,P128:Q132,2,0),"")
A33: POR PAGOS EFECTUADOS POR CONTRATOS DE SALUD NO POS
B35: NOMBRE DE LA ENTIDAD
B37: NIT ENTIDAD | U37: VALOR TOTAL PAGADO
Q39: VALOR MENSUAL | W39: ='Validador- Datos'!BM8 -> 0
B40: FECHA EXPEDICIÓN CERTIFICADO | R40: FECHA CORTE DEL CERTIFICADO
B41: =+B30 -> Como soporte se anexa la siguiente documentación:
B42: =IF(H35="","",AD44)
A44: POR PAGO DE CRÉDITOS HIPOTECARIOS | AD44: =CONCATENATE("CERTIFICADO EXPEDIDO POR ",H35," A NOMBRE DE ",J11," TITULAR DEL CONTRATO ") -> CERTIFICADO EXPEDIDO POR A NOMBRE DE TITULAR DEL CONTRATO
B46: NOMBRE DE LA ENTIDAD
B48: NIT ENTIDAD | U48: VALOR TOTAL INTERES PAGADO
Q50: VALOR MENSUAL | W50: =IF(L54="",'Validador- Datos'!BM9,'Validador- Datos'!BM9/L54) -> 0
B52: FECHA EXPEDICIÓN CERTIFICADO | R52: FECHA CORTE DEL CERTIFICADO
B54: CANTIDAD DE TITULARES DEL CRÉDITO
B56: =+B41 -> Como soporte se anexa la siguiente documentación:
B57: =IF(H46="","",AD59)
AD59: =CONCATENATE("CERTIFICADO EXPEDIDO POR ",H46," A NOMBRE DE ",,J11, " TITULAR DEL CREDITO ") -> CERTIFICADO EXPEDIDO POR A NOMBRE DE TITULAR DEL CREDITO
B60: Declaro que asumo íntegramente la responsabilidad por la veracidad de esta información, la cual puede ser comprobada por la entidad cuando lo considere.; por lo anterior cualquier falsedad en que se incurra podrá ser sancionada.
B62: No de Folios anexos
B68: =+J11
B70: Con la firma del presente formulario certificó la veracidad de la información en él consignada y autorizó a la Secretaria de Educación de Bogotá su uso para la liquidación del FURC y la actualización de la información de las bases de datos de la Entidad, en especial la de Apoteosys y la información reportada a la DIAN. Al firmar este documento, autorizo de manera previa, expresa e informada a la Secretaría de Educación del Distrito para que realice el tratamiento de mis datos personales aquí suministrados. Esta información será utilizada con fines de actualización de información del tercero, conforme a la Ley 1581 de 2012 y a la Política de Tratamiento de Datos disponible en www.educacionbogota.gov.co. Como titular, tengo derecho a conocer, actualizar, rectificar y solicitar la supresión de mis datos, así como a presentar quejas ante la Superintendencia de Industria y Comercio
B71: =+G13 -> 0 | Z71: 13-IF-016
Z72: V.1.
H84: 2018
B85: 44562 | H85: 2017
B86: 44563 | H86: 2016
B87: 44564 | F87: 1 | G87: 1 | H87: 2015 | I87: 0
B88: 44565 | F88: 2 | G88: 2 | H88: 2014 | I88: 1
B89: 44566 | F89: 3 | G89: 3 | H89: 2013 | I89: 2
B90: 44567 | F90: 4 | G90: 4 | H90: 2012 | I90: 3
B91: 44568 | F91: 5 | G91: 5 | H91: 2011 | I91: 4
B92: 44569 | F92: 6 | G92: 6 | H92: 2010 | I92: 5
B93: 44570 | F93: 7 | G93: 7 | H93: 2009 | I93: 6
B94: 44571 | F94: 8 | G94: 8 | H94: 2008 | I94: 7
B95: 44572 | F95: 9 | G95: 9 | H95: 2007 | I95: 8
B96: 44573 | F96: 10 | G96: 10 | H96: 2006 | I96: 9
B97: 44574 | F97: 11 | G97: 11 | H97: 2005 | I97: 10
B98: 44575 | F98: 12 | G98: 12 | H98: 2004 | I98: 11
B99: 44576 | G99: 13 | H99: 2003 | I99: 12
B100: 44577 | G100: 14 | H100: 2002 | I100: 13
B101: 44578 | G101: 15 | H101: 2001 | I101: 14
B102: 44579 | G102: 16 | H102: 2000 | I102: 15
B103: 44580 | G103: 17 | H103: 1999 | I103: 16
B104: 44581 | G104: 18 | H104: 1998 | I104: 17
B105: 44582 | G105: 19 | H105: 1997 | I105: 18
B106: 44583 | G106: 20 | H106: 1996 | I106: 19
B107: 44584 | G107: 21 | H107: 1995 | I107: 20
B108: 44585 | G108: 22 | H108: 1994 | I108: 21
B109: 44586 | G109: 23 | H109: 1993 | I109: 22
B110: 44587 | G110: 24 | H110: 1992 | I110: 23
... B112: 44589 | G112: 26 | H112: 1990 | I112: 25
B113: 44590 | G113: 27 | I113: 26
B114: 44591 | G114: 28 | I114: 27
B115: 44592 | G115: 29 | I115: 28
B116: 44593 | G116: 30 | I116: 29
B117: 44594 | G117: 31 | I117: 30
B118: 44595 | I118: 31
B119: 44596 | I119: 32
B120: 44597 | I120: 33
B121: 44598 | I121: 34
B122: 44599 | I122: 35
B123: 44600 | I123: 36
B124: 44601 | I124: 37
B125: 44602 | I125: 38
B126: 44603 | I126: 39
B127: 44604 | C127: Motivos | I127: 40 | Q127: Anexo
B128: 44605 | C128: 1. Los hijos del contribuyente que tengan hasta 18 años de edad y dependan económicamente del contribuyente. | I128: 41 | J128: HIJO | P128: 1 | Q128: * - No se requiere.
B129: 44606 | C129: 2. Los hijos del contribuyente con edad entre 18 y 23 años, cuando el padre o madre contribuyente persona natural se encuentre financiando su educación en instituciones formales de educación superior certificadas por el ICFES o la autoridad oficial correspondiente; o en los programas técnicos de educación no formal debidamente acreditados por la autoridad competente. | I129: 42 | J129: HIJO | P129: 2 | Q129: * - No se requiere.
B130: 44607 | C130: 3. Los hijos del contribuyente mayores de 23 años que se encuentren en situación de dependencia originada en factores físicos o psicológicos que sean certificados por Medicina Legal. | I130: 43 | J130: HIJO | P130: 3 | Q130: * - Certificación emitida por Medicina Legal o por EPS.
B131: 44608 | C131: 4. El cónyuge o compañero permanente del contribuyente que se encuentre en situación de dependencia sea por ausencia de ingresos o ingresos en el año menores a doscientos sesenta (260) UVT, certificada por contador público, o por dependencia originada en factores físicos o psicológicos que sean certificados por Medicina Legal. | I131: 44 | J131: CONYUGUE | P131: 4 | Q131: *.- Certificado de contador publico en la que conste la ausencia de ingreso o ingresos menores en el año a 260 UVT. *.- En caso de dependencia por factores físicos o psicológicos: certificado emitido por Medicina Legal o por EPS.
B132: 44609 | C132: 5. Los padres y los hermanos del contribuyente que se encuentren en situación de dependencia, sea por ausencia de ingresos o ingresos en el año menores a doscientas sesenta (260) UVT, certificada por contador público, o por dependencia originada en factores físicos o psicológicos que sean certificados por Medicina Legal. | I132: 45 | J132: COMPAÑERO PERMANENTE | P132: 5 | Q132: *.- Certificado de contador publico en la que conste la ausencia de ingreso o ingresos menores en el año a 260 UVT. *.- En caso de dependencia por factores físicos o psicológicos: certificado emitido por Medicina Legal o por EPS.
B133: 44610 | I133: 46 | J133: PADRE
B134: 44611 | I134: 47 | J134: HERMANO
B135: 44612 | I135: 48 | Q135: * - Original o copia del registro civil de nacimiento.
B136: 44613 | I136: 49 | Q136: * - Certificado de constancia de estudios del año en curso emitida por la institución de educación superior o programas técnicos de educación no formal, el cual debe contener la siguiente información : Nombre e identificación del estudiante y Nombre y Nit de la Institución Educativa. * - Original o copia del registro civil de nacimiento.
B137: 44614 | I137: 50 | Q137: * - Original o copia del registro civil de nacimiento. * - Certificación emitida por Medicina Legal o por EPS.
B138: 44615 | I138: 51 | Q138: *.- Original o copia del registro civil de matrimonio. *.- Para compañero permanente: Escritura publica de unión material de hecho o declaración de convivencia ante notario. *.- Certificado de contador publico en la que conste la ausencia de ingreso o ingresos menores en el año a 260 UVT. *.- En caso de dependencia por factores físicos o psicológicos: certificado emitido por Medicina Legal.
B139: 44616 | I139: 52 | Q139: *.- Para caso de los padres: Original o copia del registro civil del contratista. *.- Para el caso de los hermanos: Original o copia de los registros civil de nacimiento del contratista y su hermano. *.- Certificado de contador publico en la que conste la ausencia de ingreso o ingresos menores en el año a 260 UVT. *.- En caso de dependencia por factores físicos o psicológicos: certificado emitido por Medicina Legal.
B140: 44617 | I140: 53
B141: 44618 | I141: 54
B142: 44619 | I142: 55
B143: 44620 | I143: 56
B144: 44621 | I144: 57
B145: 44622 | I145: 58
...

Sheet INSTRUCTIVO DEDUCCIONES
A6: I. OBJETIVO
A7: Establecer las instrucciones para el correcto diligenciamiento del formato mediante el cual las personas naturales vinculadas mediante contrato reportan las deducciones tributarias aplicables para efectos fiscales, conforme a la normatividad vigente en Colombia y lineamientos establecidos por la Dirección de Impuestos y Aduanas Nacionales (DIAN).
A9: II. ALCANCE
A10: Este instructivo aplica a todas las personas naturales que tengan relación contractual o administrativa con la Secretaría de Educación del Distrito, tales como contratistas, prestadores de servicios que requieran registrarse o actualizar su información en la entidad. Comprende el diligenciamiento del formato, la entrega de los soportes correspondientes y la verificación de la información por parte de las áreas responsables.
A12: III. RESPONSABLE
A14: Contratista (Persona Natural) • Diligenciar completamente el formato de Excel con la información actualizada. •Aportar la documentación soporte requerida • Garantizar la veracidad de la información suministrada. Área Financiera / Tesorería / Grupo de actualizaciones de terceros • Revisar la información registrada. • Validar los datos tributarios y bancarios frente a los soportes recibidos • Utilizar la información para incluirla en el sistema Apoteosys para la liquidación de los pagos.
A16: IV. FRECUENCIA
A18: La actualización del formato debe realizarse: • Cuando exista cambio en la información tributaria o bancaria, o por cambio en la normatividad vigente y/o por ordenamiento de la Secretaría de Educación del Distrito, cuando haya lugar
A20: V. INSTRUCCIONES GENERALES DE DILIGENCIAMIENTO
A21: 1.Diligenciar el formato únicamente en las celdas habilitadas (color amarillo). 2. El formato debe diligenciarse con información veraz. 3. Los valores deben registrarse en pesos colombianos (COP). 4. Todos los campos deben completarse de acuerdo con los certificados o documentos soporte. 5. Los documentos anexos deben ser legibles y corresponder al mismo año fiscal reportado. 6. El formato debe presentarse junto con los soportes que acrediten las deducciones solicitadas.
A23: VI.DILIGENCIAMIENTO DEL FORMATO
A25: DATOS DEL TERCERO Todos los campos son datos formulados que vienen del diligenciamiento de la hoja Formato actualizacion de datos.
... A32: El diligenciamiento del presente formato implica que el declarante certifica que la información suministrada es veraz, que los documentos anexos corresponden a la realidad y que las deducciones solicitadas cumplen con los requisitos establecidos en la normativa tributaria vigente.

Sheet Validador- Datos
A1: VALIDADOR | H1: LETRAS | I1: NUMERO | K1: TIPO DE DOCUMENTO | L1: COD_DIAN | M1: COD_APOT | O1: NOMENCLATURA | P1: COD | Q1: CUADRANTE | R1: BIS | T1: PAIS | U1: Código | W1: DPTO | X1: COD_DEPTO | Z1: Cod busqueda | AA1: =+'FORMATO ACTUALIZACIÓN DATOS'!AI21 | AB1: DPTO | AC1: COD_DEPTO | AD1: cod_dep ciu | AE1: No | AF1: NOM_MPIO | AG1: COD_MPIO | AK1: NOM_MPIO | AL1: COD_MPIO | AN1: Denominación social de la Entidad | AO1: Denominación abreviada de la entidad | AP1: NIT | AQ1: Cod | AS1: CÓDIGO | AT1: AGRUPACIÓN | AU1: D E S C R I P C I Ó N | AV1: AÑO 2024 | AX1: CLASIFICACIÓN INDUSTRIAL INTERNACIONAL UNIFORME, REVISIÓN 4 ADAPTADA PARA COLOMBIA CIIU Rev. 4 A.C. | AY1: DESCRIPCIÓN | BA1: DESCRIPCIÓN DE ACTIVIDAD ECONÓMICA FINAL ARL | BB1: condigo completo | BC1: TARIFA | BE1: CODIFICACIÓN | BI1: AÑO | BJ1: UVT | BK1: LIMITE | BL1: LIMITE PESOS | BM1: VALOR CONTRATO | BN1: CONTRATO SIN IVA | BO1: IVA CONTRATO
A2: No. | B2: Val. | C2: Descripción | D2: Formula | H2: A | I2: 0 | K2: Registro civil | L2: 11 | M2: OTI | O2: Autopista | P2: AUT | Q2: SUR | R2: BIS | T2: COLOMBIA | U2: 169 | W2: Bogotá D.C | X2: 11 | AB2: Antioquia | AC2: 05 | AD2: =CONCATENATE(AC2,"-",AE2) -> 05-1 | AE2: 1 | AF2: MEDELLÍN | AG2: 001 | AI2: 1 | AJ2: =CONCATENATE($AA$1,"-",AI2) -> -1 | AK2: =IFERROR(VLOOKUP(AJ2,$AD$2:$AG$1120,3,0),"") | AL2: =IFERROR(VLOOKUP(AJ2,$AD$2:$AG$1120,4,0),"") | AN2: Banco Popular | AO2: Banco Popular | AQ2: 2 | AS2: 111 | AU2: Cultivo de cereales (excepto arroz), legumbres y semillas oleaginosas | AV2: 0 | AX2: 0010 | AY2: Asalariados | BA2: EMPRESAS DEDICADAS A ACTIVIDADES DE SERVICIOS, AGRÍCOLAS Y GANADEROS, EXCEPTO LAS ACTIVIDADES VETERINARIAS INCLUYE EL ALMACÉN Y/O DEPOSITO DE CAFÉ | BB2: 114001 | BE2: =IF('FORMATO ACTUALIZACIÓN DATOS'!AU39="RESPONSABLE IVA","C",IF('FORMATO ACTUALIZACIÓN DATOS'!AU39="NO RESPONSABLE IVA","S","ERROR")) -> ERROR | BF2: RESPONSABLE DE IVA =S | BG2: NO RESPONSABLE DE IVA=C | BI2: 2026 | BJ2: 52374 | BK2: 4000 | BL2: =BK2*BJ2 -> 209496000 | BM2: ='FORMATO ACTUALIZACIÓN DATOS'!K46 -> 0 | BN2: =ROUND(BM2/1.19,) -> 0 | BO2: =ROUND(BN2*0.19,) -> 0 | BP2: =BN2+BO2 -> 0
A3: 1 | B3: =IF('FORMATO ACTUALIZACIÓN DATOS'!A13="",0,1) -> 0 | C3: Número de Identificación Tributaria (NIT) | D3: =IF(B3=0,CONCATENATE(" - ",C3,""),"") -> - Número de Identificación Tributaria (NIT) | H3: B | I3: 1 | K3: Tarjeta de identidad | L3: 12 | M3: TI | O3: Avenida | P3: AV | Q3: ESTE | R3: BIS A | T3: AFGANISTAN | U3: 013 | W3: Amazonas | X3: 91 | AB3: Antioquia | AC3: 05 | AD3: =CONCATENATE(AC3,"-",AE3) -> 05-2 | AE3: =IF(AB3=AB2,1+AE2,1) -> 2 | AF3: ABEJORRAL | AG3: 002 | AI3: 2 | AJ3: =CONCATENATE($AA$1,"-",AI3) -> -2 | AK3: =IFERROR(VLOOKUP(AJ3,$AD$2:$AG$1120,3,0),"") | AL3: =IFERROR(VLOOKUP(AJ3,$AD$2:$AG$1120,4,0),"") | AN3: BBVA Colombia | AO3: BBVA Colombia | AQ3: 13 | AS3: 112 | AU3: Cultivo de arroz | AV3: 0 | AX3: 0081 | AY3: Personas Naturales sin Actividad Económica | BA3: Tejeduria de productos textiles, incluye produccion de hilados, tejidos y similares a mano o con equipo no motorizado. | BB3: 1131201 | BE3: =IF(OR('FORMATO ACTUALIZACIÓN DATOS'!BA61="X",'FORMATO ACTUALIZACIÓN DATOS'!BA64="X")=TRUE,"VERDADERO","FALSO") -> FALSO | BF3: ingresos del año gravable 2025 fueron superiores a $73,323,600 O declara Impuesto de Renta
A4: 2 | B4: =IF('FORMATO ACTUALIZACIÓN DATOS'!P11="",0,1) -> 0 | C4: DV | D4: =IF(B4=0,CONCATENATE(" - ",C4,""),"") -> - DV | H4: C | I4: 2 | K4: Cédula de ciudadanía | L4: 13 | M4: CC | O4: Avenida Calle | P4: AC | T4: ALBANIA | U4: 017 | W4: Antioquia | X4: 05 | AB4: Antioquia | AC4: 05 | AD4: =CONCATENATE(AC4,"-",AE4) -> 05-3 | AE4: =IF(AB4=AB3,1+AE3,1) -> 3 | AF4: ABRIAQUÍ | AG4: 004 | AI4: 3 | AJ4: =CONCATENATE($AA$1,"-",AI4) -> -3 | AK4: =IFERROR(VLOOKUP(AJ4,$AD$2:$AG$1120,3,0),"") | AL4: =IFERROR(VLOOKUP(AJ4,$AD$2:$AG$1120,4,0),"") | AN4: Banco Davivienda S.A. | AO4: Banco Davivienda S.A. | AQ4: 51 | AS4: 113 | AU4: Cultivo de hortalizas, raíces y tubérculos | AV4: 0 | AX4: 0082 | AY4: Personas Naturales Subsidiadas por Terceros | BA4: Tejeduria de productos textiles, incluye la fabricacion de articulos confeccionados de materiales textiles, a partir de tejidos de produccion propia a mano o con equipo no motorizado. | BB4: 1131202 | BE4: =IF(OR('FORMATO ACTUALIZACIÓN DATOS'!BA61="X",'FORMATO ACTUALIZACIÓN DATOS'!BA64="X")=TRUE,"SI","NO") -> NO | BF4: ingresos del año gravable 2025 fueron superiores a $73,323,600 O declara Impuesto de Renta
A5: 3 | B5: =IF('FORMATO ACTUALIZACIÓN DATOS'!R11="",0,1) -> 1 | C5: Tipo de Contribuyente | D5: =IF(B5=0,CONCATENATE(" - ",C5,""),"") | H5: D | I5: 3 | K5: Certificado de la Registraduría para sucesiones ilíquidas de personas naturales | L5: 14 | M5: OTI | O5: Avenida Carrera | P5: AK | T5: ALEMANIA | U5: 023 | W5: Arauca | X5: 81 | AB5: Antioquia | AC5: 05 | AD5: =CONCATENATE(AC5,"-",AE5) -> 05-4 | AE5: =IF(AB5=AB4,1+AE4,1) -> 4 | AF5: ALEJANDRÍA | AG5: 021 | AI5: 4 | AJ5: =CONCATENATE($AA$1,"-",AI5) -> -4 | AK5: =IFERROR(VLOOKUP(AJ5,$AD$2:$AG$1120,3,0),"") | AL5: =IFERROR(VLOOKUP(AJ5,$AD$2:$AG$1120,4,0),"") | AN5: Banco de Bogotá | AO5: Banco de Bogotá | AQ5: 1 | AS5: 114 | AU5: Cultivo de tabaco | AV5: 0 | AX5: 0090 | AY5: Rentistas de Capital, solo para personas naturales. | BA5: Fabricacion de tapetes y alfombras para pisos, incluye la fabricacion de tapices, esteras, tapetes a mano o con equipo no motorizado. | BB5: 1139301 | BE5: =IF(OR('FORMATO ACTUALIZACIÓN DATOS'!BC61="X",'FORMATO ACTUALIZACIÓN DATOS'!BC64="X")=TRUE,"SI","NO") -> NO | BF5: ingresos del año gravable 2025 NO fueron superiores a $73,323,600 O NO declara Impuesto de Renta
A6: 4 | B6: =IF('FORMATO ACTUALIZACIÓN DATOS'!AC11="",0,1) -> 0 | C6: Tipo de Documento | D6: =IF(B6=0,CONCATENATE(" - ",C6,""),"") -> - Tipo de Documento | H6: E | I6: 4 | K6: Tipo de documento que identifica una sucesión ilíquida, expedido por la Notaria o Juzgado | L6: 15 | M6: OTI | O6: Boulevard | P6: BL | T6: ANDORRA | U6: 037 | W6: SanAndres | X6: 88 | AB6: Antioquia | AC6: 05 | AD6: =CONCATENATE(AC6,"-",AE6) -> 05-5 | AE6: =IF(AB6=AB5,1+AE5,1) -> 5 | AF6: AMAGÁ | AG6: 030 | AI6: 5 | AJ6: =CONCATENATE($AA$1,"-",AI6) -> -5 | AK6: =IFERROR(VLOOKUP(AJ6,$AD$2:$AG$1120,3,0),"") | AL6: =IFERROR(VLOOKUP(AJ6,$AD$2:$AG$1120,4,0),"") | AN6: Bancolombia SA | AO6: Bancolombia SA | AQ6: 7 | AS6: 115 | AU6: Cultivo de plantas textiles | AV6: 0 | AX6: 0111 | AY6: Cultivo de cereales (excepto arroz), legumbres y semillas oleaginosas. | BA6: Confeccion de prendas de vestir, excepto prendas de piel, incluye pequeños talleres, confeccion de prendas de vestir sobre medidas y/o en serie, sombreros y gorros, incluso de piel, confeccion de ropa y confeccion de partes de los productos mencionados. | BB6: 1141001 | BE6: =IF(AND('FORMATO ACTUALIZACIÓN DATOS'!BA61="X",'FORMATO ACTUALIZACIÓN DATOS'!BC61="X",'FORMATO ACTUALIZACIÓN DATOS'!BA64="X",'FORMATO ACTUALIZACIÓN DATOS'!BC64="x")=TRUE,"SI","NO") -> NO | BF6: se llena las dos primeras preguntas de manera incongruente llenando todas las opciones | BI6: DESCRIPCIÓN | BJ6: VALOR MENSUAL | BK6: autorizado | BL6: MAXIMO ley | BM6: max. Aplicar mensual | BN6: Max Anual | BO6: max. Aplicar
A7: 5 | B7: =IF(E7=1,1,IF('FORMATO ACTUALIZACIÓN DATOS'!AP13="",0,1)) -> 0 | C7: Número de Identificación | D7: =IF(B7=0,CONCATENATE(" - ",C7,""),"") -> - Número de Identificación | E7: ='FORMATO ACTUALIZACIÓN DATOS'!AA11 -> 2 | H7: F | I7: 5 | K7: Tarjeta de extranjería | L7: 21 | M7: OTI | O7: Calle | P7: CL | T7: ANGOLA | U7: 040 | W7: Atlántico | X7: 08 | AB7: Antioquia | AC7: 05 | AD7: =CONCATENATE(AC7,"-",AE7) -> 05-6 | AE7: =IF(AB7=AB6,1+AE6,1) -> 6 | AF7: AMALFI | AG7: 031 | AI7: 6 | AJ7: =CONCATENATE($AA$1,"-",AI7) -> -6 | AK7: =IFERROR(VLOOKUP(AJ7,$AD$2:$AG$1120,3,0),"") | AL7: =IFERROR(VLOOKUP(AJ7,$AD$2:$AG$1120,4,0),"") | AN7: Banco de Occidente | AO7: Banco de Occidente | AQ7: 23 | AS7: 119 | AU7: Otros cultivos transitorios n.c.p. | AV7: 0 | AX7: 0112 | AY7: Cultivo de arroz. | BA7: TEJEDURA DE PRODUCTOS TEXTILES: HACE REFERENCIA A EMPRESAS DEDICADAS A PRODUCIR HILADOS, TEJIDOS Y SIMILARES A MANO O CON EQUIPO NO MOTORIZADO | BB7: 1172001 | BE7: =IF(AND('FORMATO ACTUALIZACIÓN DATOS'!BA61="",,'FORMATO ACTUALIZACIÓN DATOS'!BA64="")=TRUE,"SI","NO") -> NO | BI7: DEPENDIENTES | BJ7: ='FORMATO ACTUALIZACIÓN DATOS'!A50 -> 0 | BK7: =BJ7*0.1 -> 0 | BL7: {=Valor_con_IVA[UVT]*32} -> 1675968 | BM7: =MIN(BK7,BL7) -> 0 | BN7: {=384*Valor_con_IVA[UVT]} -> 20111616
A8: 5.1 | B8: ='FORMATO ACTUALIZACIÓN DATOS'!R13 -> 0 | C8: Verificar el Número de Identificación | D8: =IF(B8=0,CONCATENATE(" - ",C8,""),"") -> - Verificar el Número de Identificación | H8: G | I8: 6 | K8: Cédula de extranjería | L8: 22 | M8: CE | O8: Carrera | P8: CR | T8: ANGUILLA | U8: 041 | W8: Bogotá D.C | X8: 11 | AB8: Antioquia | AC8: 05 | AD8: =CONCATENATE(AC8,"-",AE8) -> 05-7 | AE8: =IF(AB8=AB7,1+AE7,1) -> 7 | AF8: ANDES | AG8: 034 | AI8: 7 | AJ8: =CONCATENATE($AA$1,"-",AI8) -> -7 | AK8: =IFERROR(VLOOKUP(AJ8,$AD$2:$AG$1120,3,0),"") | AL8: =IFERROR(VLOOKUP(AJ8,$AD$2:$AG$1120,4,0),"") | AN8: Banco Agrario | AO8: Banco Agrario | AQ8: 40 | AS8: 121 | AU8: Cultivo de frutas tropicales y subtropicales | AV8: 0 | AX8: 0113 | AY8: Cultivo de hortalizas, raíces y tubérculos. | BA8: FABRICACIÓN DE TAPICES Y ALFOMBRAS PARA PISOS HACE REFERENCIA A EMPRESAS DEDICADAS A LA FABRICACIÓN DE TAPETES Y SIMILARES A MANO O CON EQUIPO NO MOTORIZADO | BB8: 1174201 | BE8: =IF(AND('FORMATO ACTUALIZACIÓN DATOS'!BC61="",'FORMATO ACTUALIZACIÓN DATOS'!BC64="")=TRUE,"SI","NO") -> SI | BF8: se marco que SI las dos primeras preguntas | BI8: NO POS | BJ8: =BJ7 -> 0 | BK8: {=16*12*Valor_con_IVA[UVT]} -> 10055808 | BL8: =BK8/12 -> 837984 | BM8: =MIN(BL8,'FORMATO DEDUCCIONES'!Y37/12) -> 0 | BO8: =BL9/12 -> 436450
A9: 6 | B9: =IF(E7=1,1,IF('FORMATO ACTUALIZACIÓN DATOS'!A16="",0,1)) -> 0 | C9: Primer Apellido | D9: =IF(B9=0,CONCATENATE(" - ",C9,""),"") -> - Primer Apellido | H9: H | I9: 7 | K9: Identificación de extranjeros diferente al NIT asignado DIAN | L9: 33 | M9: OTI | O9: Carretera | P9: CRT | T9: ANTIGUA Y BARBUDA | U9: 043 | W9: Bolívar | X9: 13 | AB9: Antioquia | AC9: 05 | AD9: =CONCATENATE(AC9,"-",AE9) -> 05-8 | AE9: =IF(AB9=AB8,1+AE8,1) -> 8 | AF9: ANGELÓPOLIS | AG9: 036 | AI9: 8 | AJ9: =CONCATENATE($AA$1,"-",AI9) -> -8 | AK9: =IFERROR(VLOOKUP(AJ9,$AD$2:$AG$1120,3,0),"") | AL9: =IFERROR(VLOOKUP(AJ9,$AD$2:$AG$1120,4,0),"") | AN9: Banco Davibank | AO9: Banco Davibank | AQ9: 19 | AS9: 122 | AU9: Cultivo de plátano y banano | AV9: 0 | AX9: 0114 | AY9: Cultivo de tabaco. | BA9: FABRICACIÓN DE PRENDAS DE VESTIR, EXCEPTO PRENDAS: PEQUEÑOS TALLERES DE MODAS, SASTRERÍAS, SOMBREROS, CONFECCIONES DE ROPA | BB9: 1181001 | BE9: =CONCATENATE('FORMATO ACTUALIZACIÓN DATOS'!BA61,'FORMATO ACTUALIZACIÓN DATOS'!BC61) | BF9: si hay 2 X´s se llena de manera erronea | BI9: INTERESES | BJ9: =BJ8 -> 0 | BK9: ='FORMATO DEDUCCIONES'!Y48/12 -> 0 | BL9: {=100*Valor_con_IVA[UVT]} -> 5237400 | BM9: =MIN(BK9,BL9) -> 0
A10: 7 | B10: =IF(E7=1,1,IF('FORMATO ACTUALIZACIÓN DATOS'!Q16="",0,1)) -> 0 | C10: Primer Nombre | D10: =IF(B10=0,CONCATENATE(" - ",C10,""),"") -> - Primer Nombre | H10: I | I10: 8 | K10: Pasaporte | L10: 41 | M10: OTI | O10: Circunvalar | P10: CV | T10: ANTILLAS HOLANDESAS | U10: 047 | W10: Boyacá | X10: 15 | AB10: Antioquia | AC10: 05 | AD10: =CONCATENATE(AC10,"-",AE10) -> 05-9 | AE10: =IF(AB10=AB9,1+AE9,1) -> 9 | AF10: ANGOSTURA | AG10: 038 | AI10: 9 | AJ10: =CONCATENATE($AA$1,"-",AI10) -> -9 | AK10: =IFERROR(VLOOKUP(AJ10,$AD$2:$AG$1120,3,0),"") | AL10: =IFERROR(VLOOKUP(AJ10,$AD$2:$AG$1120,4,0),"") | AN10: Banco Caja Social BCSC SA | AO10: Banco Caja Social BCSC SA | AQ10: 32 | AS10: 123 | AU10: Cultivo de café | AV10: 0 | AX10: 0115 | AY10: Cultivo de plantas textiles. | BA10: Comercio comercio al por mayor y al por menor de motocicletas de sus partes, piezas y accesorios; incluye pequeños establecimientos comerciales que se dedican al mantenimiento y reparacion de motocicletas de pequeña potencia o ciclomotores y trineos motorizados, nuevos y usados, sus partes, piezas y accesorios. | BB10: 1454101 | BE10: =LEN(BE9) -> 0
A11: 8 | B11: =IF(AND('FORMATO ACTUALIZACIÓN DATOS'!Q18="x",'FORMATO ACTUALIZACIÓN DATOS'!S18="x"),0,IF(OR('FORMATO ACTUALIZACIÓN DATOS'!Q18="x",'FORMATO ACTUALIZACIÓN DATOS'!S18="x"),1,0)) -> 0 | C11: Indicar SI es o NO pensionado | D11: =IF(B11=0,CONCATENATE(" - ",C11,""),"") -> - Indicar SI es o NO pensionado | H11: J | I11: 9 | K11: Documento de identificación extranjero | L11: 42 | M11: OTI | O11: Circular | P11: CV | T11: ARABIA SAUDITA | U11: 053 | W11: Caldas | X11: 17 | AB11: Antioquia | AC11: 05 | AD11: =CONCATENATE(AC11,"-",AE11) -> 05-10 | AE11: =IF(AB11=AB10,1+AE10,1) -> 10 | AF11: ANORÍ | AG11: 040 | AI11: 10 | AJ11: =CONCATENATE($AA$1,"-",AI11) -> -10 | AK11: =IFERROR(VLOOKUP(AJ11,$AD$2:$AG$1120,3,0),"") | AL11: =IFERROR(VLOOKUP(AJ11,$AD$2:$AG$1120,4,0),"") | AN11: Banco GNB Sudameris | AO11: Banco GNB Sudameris | AQ11: 12 | AS11: 124 | AU11: Cultivo de caña de azúcar | AV11: 0 | AX11: 0119 | AY11: Otros cultivos transitorios n.c.p. | BA11: Mantenimiento y reparacion de motocicletas y de sus partes y piezas, incluye las actividades de mantenimiento y reparacion de motocicletas y trineos motorizados, asi como de todo tipo de partes y piezas de los mismos. | BB11: 1454201 | BE11: =CONCATENATE('FORMATO ACTUALIZACIÓN DATOS'!BA64,'FORMATO ACTUALIZACIÓN DATOS'!BC64) | BF11: si hay 2 X´s se llena de manera erronea
A12: 9 | B12: =IF('FORMATO ACTUALIZACIÓN DATOS'!AC18="",0,1) -> 0 | C12: Indique la Dirección tal y como aparece en el RUT | D12: =IF(B12=0,CONCATENATE(" - ",C12,""),"") -> - Indique la Dirección tal y como aparece en el RUT | H12: K | K12: Sin identificación del exterior o para uso definido por la DIAN. | L12: 43 | M12: OTI | O12: Diagonal | P12: DG | T12: ARGELIA | U12: 059 | W12: Caquetá | X12: 18 | AB12: Antioquia | AC12: 05 | AD12: =CONCATENATE(AC12,"-",AE12) -> 05-11 | AE12: =IF(AB12=AB11,1+AE11,1) -> 11 | AF12: SANTAFÉ DE ANTIOQUIA | AG12: 042 | AI12: 11 | AJ12: =CONCATENATE($AA$1,"-",AI12) -> -11 | AK12: =IFERROR(VLOOKUP(AJ12,$AD$2:$AG$1120,3,0),"") | AL12: =IFERROR(VLOOKUP(AJ12,$AD$2:$AG$1120,4,0),"") | AN12: Citibank | AO12: Citibank | AQ12: 9 | AS12: 125 | AU12: Cultivo de flor de corte | AV12: 0 | AX12: 0121 | AY12: Cultivo de frutas tropicales y subtropicales. | BA12: Comercio al por mayor a cambio de una retribucion o por contrata, incluye la a venta de: materias primas agropecuarias, animales vivos y aves muertas. | BB12: 1461001 | BE12: =LEN(BE11) -> 0 | BI12: ='FORMATO DEDUCCIONES'!W15 -> 46204 | BJ12: =IF(BI13<BI12,BJ13,IF(BI12<BI13,2021,2022)) -> 2025 | BK12: =MIN(BJ12:BJ16) -> 2025
A13: 10 | B13: =IF('FORMATO ACTUALIZACIÓN DATOS'!AI21="",0,1) -> 0 | C13: País | D13: =IF(B13=0,CONCATENATE(" - ",C13,""),"") -> - País | H13: L | K13: Documento de Identificación extranjero Persona Jurídica | L13: 44 | M13: OTI | O13: Kilómetro | P13: KM | T13: ARGENTINA | U13: 063 | W13: Casanare | X13: 85 | AB13: Antioquia | AC13: 05 | AD13: =CONCATENATE(AC13,"-",AE13) -> 05-12 | AE13: =IF(AB13=AB12,1+AE12,1) -> 12 | AF13: ANZA | AG13: 044 | AI13: 12 | AJ13: =CONCATENATE($AA$1,"-",AI13) -> -12 | AK13: =IFERROR(VLOOKUP(AJ13,$AD$2:$AG$1120,3,0),"") | AL13: =IFERROR(VLOOKUP(AJ13,$AD$2:$AG$1120,4,0),"") | AN13: Banco Santander de Negocios Colombia S.A. | AO13: Banco Santander de Negocios Colombia S.A. | AQ13: 65 | AS13: 126 | AU13: Cultivo de palma para aceite (palma africana) y otros frutos oleaginosos | AV13: 0 | AX13: 0122 | AY13: Cultivo de plátano y banano. | BA13: Comercio al por mayor a cambio de una retribucion o por contrata, incluye agentes dedicados a la venta de: materias primas agropecuarias, bebidas y tabaco; productos semiacabados textiles, prendas de vestir, pieles, casas de subasta al por mayor y comisionistas y otros mayoristas que comercian en nombre y por cuenta de terceros; actividades de las personas que ponen en contacto a vendedores y compradores y realizan transacciones comerciales en nombre de un ordenante (comprador), incluidas las realizadas por internet. | BB13: 1461002 | BE13: =BE12+BE10 -> 0 | BI13: 45017 | BJ13: =IF(BI14<BI12,BJ14,IF(BI12<BI14,2022,2023)) -> 2025
A14: 11 | B14: =IF(OR('FORMATO ACTUALIZACIÓN DATOS'!P21="169",'FORMATO ACTUALIZACIÓN DATOS'!P21=""),IF('FORMATO ACTUALIZACIÓN DATOS'!T21="",0,1),1) -> 0 | C14: Departamento | D14: =IF(B14=0,CONCATENATE(" - ",C14,""),"") -> - Departamento | H14: M | K14: Carné Diplomático: Documento expedido por el Ministerio de Relaciones | L14: 46 | M14: OTI | O14: Pasaje | P14: PJ | T14: ARMENIA | U14: 026 | W14: Cauca | X14: 19 | AB14: Antioquia | AC14: 05 | AD14: =CONCATENATE(AC14,"-",AE14) -> 05-13 | AE14: =IF(AB14=AB13,1+AE13,1) -> 13 | AF14: APARTADÓ | AG14: 045 | AI14: 13 | AJ14: =CONCATENATE($AA$1,"-",AI14) -> -13 | AK14: =IFERROR(VLOOKUP(AJ14,$AD$2:$AG$1120,3,0),"") | AL14: =IFERROR(VLOOKUP(AJ14,$AD$2:$AG$1120,4,0),"") | AN14: Banco AV Villas | AO14: Banco AV Villas | AQ14: 52 | AS14: 127 | AU14: Cultivo de plantas con las que se prepararan bebidas | AV14: 0 | AX14: 0123 | AY14: Cultivo de café. | BA14: Comercio al por mayor de materias primas agropecuarias; animales vivos, incluye granos y semillas, frutos oleaginosos, flores, plantas y sus partes, tabaco en bruto, cafe pergamino (incluida la pasilla de produccion), cafe trillado. | BB14: 1462001 | BE14: =IF(BE13=2,IF(AND(BE6="NO",BE7="NO")=TRUE,IF(BE3="VERDADERO","D",IF(OR('FORMATO ACTUALIZACIÓN DATOS'!BC61="X",'FORMATO ACTUALIZACIÓN DATOS'!BC64="X")=TRUE,"N","ERROR 3")),"ERROR 1"),"ERROR 4") -> ERROR 4 | BI14: 45383 | BJ14: =IF(BI15<BI12,BJ15,IF(BI12<BI15,2023,2024)) -> 2025
A15: 12 | B15: =IF(OR('FORMATO ACTUALIZACIÓN DATOS'!P21="169",'FORMATO ACTUALIZACIÓN DATOS'!P21=""),IF('FORMATO ACTUALIZACIÓN DATOS'!AM21="",0,1),1) -> 0 | C15: Municipio | D15: =IF(B15=0,CONCATENATE(" - ",C15,""),"") -> - Municipio | H15: N | O15: Paseo | P15: PS | T15: ARUBA | U15: 027 | W15: Cesar | X15: 20 | AB15: Antioquia | AC15: 05 | AD15: =CONCATENATE(AC15,"-",AE15) -> 05-14 | AE15: =IF(AB15=AB14,1+AE14,1) -> 14 | AF15: ARBOLETES | AG15: 051 | AI15: 14 | AJ15: =CONCATENATE($AA$1,"-",AI15) -> -14 | AK15: =IFERROR(VLOOKUP(AJ15,$AD$2:$AG$1120,3,0),"") | AL15: =IFERROR(VLOOKUP(AJ15,$AD$2:$AG$1120,4,0),"") | AN15: DAVIVIENDA INTERNATIONAL | AO15: DAVIVIENDA INTERNATIONAL | AQ15: 998 | AS15: 128 | AU15: Cultivo de especias y de plantas aromáticas y medicinales | AV15: 0 | AX15: 0124 | AY15: Cultivo de caña de azúcar. | BA15: Comercio al por mayor de materias primas agropecuarias; animales vivos incluye, comercio al por mayor de frutos y plantas ornamentales. | BB15: 1462002 | BE15: =IF(AND('FORMATO ACTUALIZACIÓN DATOS'!BA67="X",'FORMATO ACTUALIZACIÓN DATOS'!BC67="X")=TRUE,"ERROR",IF('FORMATO ACTUALIZACIÓN DATOS'!BA67="X","SY",IF('FORMATO ACTUALIZACIÓN DATOS'!BC67="X",""))) -> FALSE | BF15: SI SE LLENA LAS DOS OPCIONES DE PREGUNTA 3 HAY ERROR | BI15: 45748 | BJ15: =IF(BI16<BI12,BJ16,IF(BI12<BI16,2024,2025)) -> 2025
A16: 13 | B16: =IF('FORMATO ACTUALIZACIÓN DATOS'!A24="",0,1) -> 1 | C16: Correo Electrónico Reportado en el RUT | D16: =IF(B16=0,CONCATENATE(" - ",C16,""),"") | H16: Ñ | K16: TIPO DE CONTRIBUYENTE | L16: COD | O16: Transversal | P16: TV | T16: AUSTRALIA | U16: 069 | W16: Chocó | X16: 27 | AB16: Antioquia | AC16: 05 | AD16: =CONCATENATE(AC16,"-",AE16) -> 05-15 | AE16: =IF(AB16=AB15,1+AE15,1) -> 15 | AF16: ARGELIA | AG16: 055 | AI16: 15 | AJ16: =CONCATENATE($AA$1,"-",AI16) -> -15 | AK16: =IFERROR(VLOOKUP(AJ16,$AD$2:$AG$1120,3,0),"") | AL16: =IFERROR(VLOOKUP(AJ16,$AD$2:$AG$1120,4,0),"") | AN16: CITIBANK OF NEW YORK | AO16: CITIBANK OF NEW YORK | AQ16: 999 | AS16: 129 | AU16: Otros cultivos permanentes n.c.p. | AV16: 0 | AX16: 0125 | AY16: Cultivo de flor de corte. | BA16: Comercio al por mayor de materias primas agropecuarias; animales vivos incluye comercio al por mayor de materias primas agropecuarias; animales vivos y sus productos pieles en bruto, cueros, materiales, desperdicios, residuos y subproductos agropecuarios que se utilizan para producir alimentos para animales. | BB16: 1462003 | BE16: T | BF16: dos (2) o mas trabajadores= O | BG16: NO SE NECESITAN dos (2) o mas trabajadores = T | BI16: 46113 | BJ16: =IF(BI17<BI12,BJ17,IF(BI12<BI17,2025,2026)) -> 2025
A17: 14 | B17: =IF('FORMATO ACTUALIZACIÓN DATOS'!AG26="",0,1) -> 0 | C17: Teléfono 1 | D17: =IF(B17=0,CONCATENATE(" - ",C17,""),"") -> - Teléfono 1 | H17: O | K17: PERSONA JURÍDICA | L17: 1 | O17: Troncal | P17: TC | T17: AUSTRIA | U17: 072 | W17: Córdoba | X17: 23 | AB17: Antioquia | AC17: 05 | AD17: =CONCATENATE(AC17,"-",AE17) -> 05-16 | AE17: =IF(AB17=AB16,1+AE16,1) -> 16 | AF17: ARMENIA | AG17: 059 | AI17: 16 | AJ17: =CONCATENATE($AA$1,"-",AI17) -> -16 | AK17: =IFERROR(VLOOKUP(AJ17,$AD$2:$AG$1120,3,0),"") | AL17: =IFERROR(VLOOKUP(AJ17,$AD$2:$AG$1120,4,0),"") | AN17: MUFG BANK LTD. - NEW YORK | AO17: MUFG BANK LTD. - NEW YORK | AQ17: 997 | AS17: 130 | AU17: Propagación de plantas (actividades de los viveros, excepto viveros forestales) | AV17: 0 | AX17: 0126 | AY17: Cultivo de palma para aceite (palma africana) y otros frutos oleaginosos. | BA17: Comercio al por mayor de productos alimenticios, incluye ventas de frutas, legumbres y hortalizas, productos lacteos, huevos y productos de huevos, aceites y grasas comestibles, productos de confiteria, panaderia y productos farinaceos, cafe transformado, te, cacao y chocolate y especias, salsas, y otros preparados alimenticios. | BB17: 1463101 | BE17: =IF(AND('FORMATO ACTUALIZACIÓN DATOS'!BA70="X",'FORMATO ACTUALIZACIÓN DATOS'!BC70="X")=TRUE,"ERROR",IF(AND('FORMATO ACTUALIZACIÓN DATOS'!BA70="",'FORMATO ACTUALIZACIÓN DATOS'!BC70="")=TRUE,"ERROR","")) -> ERROR | BF17: SI SE LLENA O NO LAS DOS OPCIONES DE PREGUNTA 5 HAY ERROR | BI17: 46478
A18: 15 | B18: =IF('FORMATO ACTUALIZACIÓN DATOS'!AQ26="",0,1) -> 0 | C18: Teléfono 2 | D18: =IF(B18=0,CONCATENATE(" - ",C18,""),"") -> - Teléfono 2 | H18: P | K18: PERSONA NATURAL | L18: 2 | O18: Variante | P18: VT | T18: AZERBAIJAN | U18: 074 | W18: Cundinamarca | X18: 25 | AB18: Antioquia | AC18: 05 | AD18: =CONCATENATE(AC18,"-",AE18) -> 05-17 | AE18: =IF(AB18=AB17,1+AE17,1) -> 17 | AF18: BARBOSA | AG18: 079 | AI18: 17 | AJ18: =CONCATENATE($AA$1,"-",AI18) -> -17 | AK18: =IFERROR(VLOOKUP(AJ18,$AD$2:$AG$1120,3,0),"") | AL18: =IFERROR(VLOOKUP(AJ18,$AD$2:$AG$1120,4,0),"") | AN18: Itaú Corpbanca Colombia S.A | AO18: Itaú Corpbanca Colombia S.A | AQ18: 6 | AS18: 141 | AU18: Cría de ganado bovino y bufalino | AV18: 0 | AX18: 0127 | AY18: Cultivo de plantas con las que se preparan bebidas. | BA18: Comercio al por mayor de productos alimenticios, incluye el comercio al por mayor de alimentos procesados para animales domesticos. | BB18: 1463102 | BE18: =LEN(CONCATENATE('FORMATO ACTUALIZACIÓN DATOS'!BA70,'FORMATO ACTUALIZACIÓN DATOS'!BC70)) -> 0
A19: 16 | B19: =IF('FORMATO ACTUALIZACIÓN DATOS'!M31="",0,1) -> 0 | C19: Banco | D19: =IF(B19=0,CONCATENATE(" - ",C19,""),"") -> - Banco | H19: Q | O19: Vereda | P19: VRD | T19: BAHAMAS | U19: 077 | W19: Guainía | X19: 94 | AB19: Antioquia | AC19: 05 | AD19: =CONCATENATE(AC19,"-",AE19) -> 05-18 | AE19: =IF(AB19=AB18,1+AE18,1) -> 18 | AF19: BELMIRA | AG19: 086 | AI19: 18 | AJ19: =CONCATENATE($AA$1,"-",AI19) -> -18 | AK19: =IFERROR(VLOOKUP(AJ19,$AD$2:$AG$1120,3,0),"") | AL19: =IFERROR(VLOOKUP(AJ19,$AD$2:$AG$1120,4,0),"") | AN19: BANCO GENERAL TRANSITORIAS TRM | AO19: BANCO GENERAL TRANSITORIAS TRM | AQ19: 990 | AS19: 142 | AU19: Cría de caballos y otros equinos | AV19: 0 | AX19: 0128 | AY19: Cultivo de especias y de plantas aromáticas y medicinales. | BA19: Comercio al por mayor de productos textiles, productos confeccionados para uso domestico, incluye .comercio al por mayor de todo tipo de productos textiles, elaborados con fibras naturales, artificiales, sinteticas y sus mezclas, hilados, tejidos y telas en general; comercio al por mayor de lenceria y productos confeccionados para uso domestico, como: frazadas,mantas de viaje, ropa de cama, cortinas, cenefas, entre otros, y otros articulos para el hogar, confeccionados con tejidos de cualquier material textil; comercio al por mayor de materiales basicos para fabricar alfombras y tapices; comercio al por mayor de articulos de merceria: agujas, hilo para coser, entre otros. | BB19: 1464101 | BE19: =IF(AND('FORMATO ACTUALIZACIÓN DATOS'!BA70="X",'FORMATO ACTUALIZACIÓN DATOS'!BC70="X")=TRUE,"ERROR",CONCATENATE("N",BE16,BE14,BE2)) -> NTERROR 4ERROR
A20: 17 | B20: =IF('FORMATO ACTUALIZACIÓN DATOS'!Q31="",0,1) -> 0 | C20: Sucursal | D20: =IF(B20=0,CONCATENATE(" - ",C20,""),"") -> - Sucursal | H20: R | T20: BAHREIN | U20: 080 | W20: Guaviare | X20: 95 | AB20: Antioquia | AC20: 05 | AD20: =CONCATENATE(AC20,"-",AE20) -> 05-19 | AE20: =IF(AB20=AB19,1+AE19,1) -> 19 | AF20: BELLO | AG20: 088 | AI20: 19 | AJ20: =CONCATENATE($AA$1,"-",AI20) -> -19 | AK20: =IFERROR(VLOOKUP(AJ20,$AD$2:$AG$1120,3,0),"") | AL20: =IFERROR(VLOOKUP(AJ20,$AD$2:$AG$1120,4,0),"") | AN20: Bancoldex | AO20: Bancoldex | AQ20: 800 | AS20: 143 | AU20: Cría de ovejas y cabras | AV20: 0 | AX20: 0129 | AY20: Otros cultivos permanentes n.c.p. | BA20: Comercio al por mayor de prendas de vestir, incluye todo tipo de prendas de vestir (incluso las prendas de vestir de cuero), para hombres, mujeres, niños y bebes ropa interior, de dormir, de etiqueta, de trabajo, para practicar deportes, entre otros y de todo tipo de accesorios para prendas de vestir y de articulos elaborados en piel | BB20: 1464201
A21: 18 | B21: =IF('FORMATO ACTUALIZACIÓN DATOS'!AE31="",0,1) -> 0 | C21: Tipo Cuenta | D21: =IF(B21=0,CONCATENATE(" - ",C21,""),"") -> - Tipo Cuenta | H21: S | K21: REGIMEN | L21: SIGLA | T21: BANGLADESH | U21: 081 | W21: Huila | X21: 41 | AB21: Antioquia | AC21: 05 | AD21: =CONCATENATE(AC21,"-",AE21) -> 05-20 | AE21: =IF(AB21=AB20,1+AE20,1) -> 20 | AF21: BETANIA | AG21: 091 | AI21: 20 | AJ21: =CONCATENATE($AA$1,"-",AI21) -> -20 | AK21: =IFERROR(VLOOKUP(AJ21,$AD$2:$AG$1120,3,0),"") | AL21: =IFERROR(VLOOKUP(AJ21,$AD$2:$AG$1120,4,0),"") | AN21: SIN CUENTA - EFECTIVO | AO21: SIN CUENTA - EFECTIVO | AQ21: CJA | AS21: 144 | AU21: Cría de ganado porcino | AV21: 0 | AX21: 0130 | AY21: Propagación de plantas (actividades de los viveros, excepto viveros forestales). | BA21: Comercio al por mayor de calzado de cualquier material y para todo uso y partes para calzado. | BB21: 1464301 | BE21: =IF(OR(BE18=2,BE18=0),"REVISE SU INFORMACIÓN TRIBUTARIA",IF(BE15="SY",CONCATENATE("N",BE15,BG23),CONCATENATE("N",BE15,BE2))) -> REVISE SU INFORMACIÓN TRIBUTARIA
A22: 19 | B22: =IF('FORMATO ACTUALIZACIÓN DATOS'!AN32="",0,1) -> 0 | C22: No Cuenta Bancaria | D22: =IF(B22=0,CONCATENATE(" - ",C22,""),"") -> - No Cuenta Bancaria | H22: T | K22: RESPONSABLE IVA | L22: RC | O22: FORMATO SED - CON ANEXOS | T22: BARBADOS | U22: 083 | W22: La Guajira | X22: 44 | AB22: Antioquia | AC22: 05 | AD22: =CONCATENATE(AC22,"-",AE22) -> 05-21 | AE22: =IF(AB22=AB21,1+AE21,1) -> 21 | AF22: BETULIA | AG22: 093 | AI22: 21 | AJ22: =CONCATENATE($AA$1,"-",AI22) -> -21 | AK22: =IFERROR(VLOOKUP(AJ22,$AD$2:$AG$1120,3,0),"") | AL22: =IFERROR(VLOOKUP(AJ22,$AD$2:$AG$1120,4,0),"") | AN22: Banco W S.A | AO22: Banco W S.A | AQ22: 53 | AS22: 145 | AU22: Cría de aves de corral | AV22: 0 | AX22: 0141 | AY22: Cría de ganado bovino y bufalino. | BA22: Comercio al por mayor de aparatos y equipo de uso domestico, incluye electrodomesticos y gas domestico, refrigeradores, lavadoras, maquinas para secar ropa, maquinas lavaplatos, aspiradoras, aparatos para calefaccion, hornos, asadores, estufas, calentadores, entre otros, para uso domestico, amplificadores, consolas, parlantes, equipos de reproduccion de sonido, radio television y comunicaciones, discos, cintas, CD, DVD, Blu-ray Disc y demas dispositivos de almacenamiento de audio y de video grabados | BB22: 1464401 | BE22: =IF(AND(BE15="",BE17=""),BE19,BE21) -> REVISE SU INFORMACIÓN TRIBUTARIA
A23: 20 | B23: =IF('FORMATO ACTUALIZACIÓN DATOS'!A40="",0,1) -> 0 | C23: Actividad Económica RUT | D23: =IF(B23=0,CONCATENATE(" - ",C23,""),"") -> - Actividad Económica RUT | H23: U | K23: NO RESPONSABLE IVA | L23: RS | T23: BELGICA | U23: 087 | W23: Magdalena | X23: 47 | AB23: Antioquia | AC23: 05 | AD23: =CONCATENATE(AC23,"-",AE23) -> 05-22 | AE23: =IF(AB23=AB22,1+AE22,1) -> 22 | AF23: CIUDAD BOLÍVAR | AG23: 101 | AI23: 22 | AJ23: =CONCATENATE($AA$1,"-",AI23) -> -22 | AK23: =IFERROR(VLOOKUP(AJ23,$AD$2:$AG$1120,3,0),"") | AL23: =IFERROR(VLOOKUP(AJ23,$AD$2:$AG$1120,4,0),"") | AN23: Banco de las Microfinanzas - Bancamia | AO23: Banco de las Microfinanzas - Bancamia | AQ23: 59 | AS23: 149 | AU23: Cría de otros animales n.c.p. | AV23: 0 | AX23: 0142 | AY23: Cría de caballos y otros equinos. | BA23: Comercio al por mayor de aparatos y equipo de uso domestico, incluye el comercio al por mayor de articulos y utensilios de uso domestico tales como cubiertos, vajillas, articulos de iluminacion, cristaleria, articulos de ceramica y utensilios de madera, de mimbre y de corcho para mesa, tocador, cocina o similares | BB23: 1464402 | BE23: =_xlfn.CONCAT(IF(LEN(BE22)>4,"REVISE SU INFORMACIÓN TRIBUTARIA",BE22),BE25) -> REVISE SU INFORMACIÓN TRIBUTARIA | BG23: =IF('FORMATO ACTUALIZACIÓN DATOS'!AU39="RESPONSABLE IVA","M",IF('FORMATO ACTUALIZACIÓN DATOS'!AU39="NO RESPONSABLE IVA","S","ERROR")) -> ERROR
A24: 21 | B24: =IF('FORMATO ACTUALIZACIÓN DATOS'!A40="",0,IF('FORMATO ACTUALIZACIÓN DATOS'!F39="Actividad economica no existe - por favor verificar",0,1)) -> 0 | C24: Actividad económica RUT NO existe - por favor verificar | D24: =IF(B24=0,CONCATENATE(" - ",C24,""),"") -> - Actividad económica RUT NO existe - por favor verificar | H24: V | T24: BELICE | U24: 088 | W24: Meta | X24: 50 | AB24: Antioquia | AC24: 05 | AD24: =CONCATENATE(AC24,"-",AE24) -> 05-23 | AE24: =IF(AB24=AB23,1+AE23,1) -> 23 | AF24: BRICEÑO | AG24: 107 | AI24: 23 | AJ24: =CONCATENATE($AA$1,"-",AI24) -> -23 | AK24: =IFERROR(VLOOKUP(AJ24,$AD$2:$AG$1120,3,0),"") | AL24: =IFERROR(VLOOKUP(AJ24,$AD$2:$AG$1120,4,0),"") | AN24: Banco Pichincha | AO24: Banco Pichincha | AQ24: 60 | AS24: 150 | AU24: Explotación primaria mixta (agrícola y pecuaria) | AV24: 0 | AX24: 0143 | AY24: Cría de ovejas y cabras. | BA24: Comercio al por mayor de productos farmaceuticos, medicinales, cosmeticos y de tocador, incluye productos farmaceuticos y medicinales, productos botanicos, articulos de perfumeria, cosmeticos y jabones de tocador y jabones detergentes, ademas de los preparados organicos tensoactivos envase y empaque de dichos productos, cuando se realiza por cuenta propia | BB24: 1464501
A25: 22 | B25: =IF('FORMATO ACTUALIZACIÓN DATOS'!X40="",0,1) -> 0 | C25: Actividad Económica RIT | D25: =IF(B25=0,CONCATENATE(" - ",C25,""),"") -> - Actividad Económica RIT | H25: W | K25: VALOR DIA | L25: VALOR | T25: BELORUS | U25: 091 | W25: Nariño | X25: 52 | AB25: Antioquia | AC25: 05 | AD25: =CONCATENATE(AC25,"-",AE25) -> 05-24 | AE25: =IF(AB25=AB24,1+AE24,1) -> 24 | AF25: BURITICÁ | AG25: 113 | AI25: 24 | AJ25: =CONCATENATE($AA$1,"-",AI25) -> -24 | AK25: =IFERROR(VLOOKUP(AJ25,$AD$2:$AG$1120,3,0),"") | AL25: =IFERROR(VLOOKUP(AJ25,$AD$2:$AG$1120,4,0),"") | AN25: Bancoomeva | AO25: Bancoomeva | AQ25: 61 | AS25: 161 | AT25: 304 | AU25: Actividades de apoyo a la agricultura | AV25: 9.66 | AX25: 0144 | AY25: Cría de ganado porcino. | BA25: Comercio al por mayor de productos farmaceuticos, medicinales, cosmeticos y de tocador, incluye el comercio al por mayor de articulos ortesicos y protesicos, drogas veterinarias y articulos para uso veterinario; envase y empaque de dichos productos, cuando se realiza por cuenta propia. | BB25: 1464502 | BE25: =IF('FORMATO ACTUALIZACIÓN DATOS'!Q18="X"," /PENSIONADO","")
A26: 23 | B26: =IF('FORMATO ACTUALIZACIÓN DATOS'!X40="",0,IF('FORMATO ACTUALIZACIÓN DATOS'!AD39="Actividad economica no existe - por favor verificar",0,1)) -> 0 | C26: Actividad economica RIT NO existe - por favor verificar | D26: =IF(B26=0,CONCATENATE(" - ",C26,""),"") -> - Actividad economica RIT NO existe - por favor verificar | H26: X | K26: VALOR DE CONTRATO | L26: ='FORMATO ACTUALIZACIÓN DATOS'!K46 -> 0 | T26: BENIN | U26: 229 | W26: Norte de Santander | X26: 54 | AB26: Antioquia | AC26: 05 | AD26: =CONCATENATE(AC26,"-",AE26) -> 05-25 | AE26: =IF(AB26=AB25,1+AE25,1) -> 25 | AF26: CÁCERES | AG26: 120 | AI26: 25 | AJ26: =CONCATENATE($AA$1,"-",AI26) -> -25 | AK26: =IFERROR(VLOOKUP(AJ26,$AD$2:$AG$1120,3,0),"") | AL26: =IFERROR(VLOOKUP(AJ26,$AD$2:$AG$1120,4,0),"") | AN26: Confiar Cooperativa Financiera | AO26: Confiar Cooperativa Financiera | AQ26: 292 | AS26: 162 | AT26: 304 | AU26: Actividades de apoyo a la ganadería | AV26: 9.66 | AX26: 0145 | AY26: Cría de aves de corral. | BA26: Comercio al por mayor de otros utensilios domesticos ncp, incluye: muebles colchones, somieres y articulos de uso domestico ncp, bicicletas sus partes y accesorios, material de limpieza y pulido (desodorizadores de ambientes, ceras artificiales, betunes, entre otros), articulos fotograficos y opticos (ej: gafas de sol, binoculares, lupas), juegos, juguetes, articulos de piñateria, relojes y articulos de joyeria, articulos deportivos, articulos de viaje, de cuero natural y de imitacion de cuero, maletas, bolsos de mano, carteras, y articulos de talabarteria y guarnicioneria (sillas de montar), paraguas, instrumentos musicales, articulos de papeleria, libros, revistas y periodicos entre otros | BB26: 1464901
A27: 24 | B27: =IF('FORMATO ACTUALIZACIÓN DATOS'!AU39="",0,1) -> 0 | C27: Régimen | D27: =IF(B27=0,CONCATENATE(" - ",C27,""),"") -> - Régimen | H27: Y | K27: VALOR MENSUAL | L27: ='FORMATO ACTUALIZACIÓN DATOS'!A50 -> 0 | T27: BERMUDAS | U27: 090 | W27: Putumayo | X27: 86 | AB27: Antioquia | AC27: 05 | AD27: =CONCATENATE(AC27,"-",AE27) -> 05-26 | AE27: =IF(AB27=AB26,1+AE26,1) -> 26 | AF27: CAICEDO | AG27: 125 | AI27: 26 | AJ27: =CONCATENATE($AA$1,"-",AI27) -> -26 | AK27: =IFERROR(VLOOKUP(AJ27,$AD$2:$AG$1120,3,0),"") | AL27: =IFERROR(VLOOKUP(AJ27,$AD$2:$AG$1120,4,0),"") | AN27: Banco Mibanco S.A. | AO27: Banco Mibanco S.A. | AQ27: 67 | AS27: 163 | AU27: Actividades posteriores a la cosecha | AV27: 0 | AX27: 0149 | AY27: Cría de otros animales n.c.p. | BA27: Comercio al por mayor de computadores, equipo periferico y programas de informatica | BB27: 1465101
A28: 25 | B28: =IF('FORMATO ACTUALIZACIÓN DATOS'!A46="",0,1) -> 0 | C28: No Contrato | D28: =IF(B28=0,CONCATENATE(" - ",C28,""),"") -> - No Contrato | H28: Z | K28: DIAS | L28: =IFERROR(((L26*30)/L27)," ") | T28: BIRMANIA (MYANMAR) | U28: 093 | W28: Quindio | X28: 63 | AB28: Antioquia | AC28: 05 | AD28: =CONCATENATE(AC28,"-",AE28) -> 05-27 | AE28: =IF(AB28=AB27,1+AE27,1) -> 27 | AF28: CALDAS | AG28: 129 | AI28: 27 | AJ28: =CONCATENATE($AA$1,"-",AI28) -> -27 | AK28: =IFERROR(VLOOKUP(AJ28,$AD$2:$AG$1120,3,0),"") | AL28: =IFERROR(VLOOKUP(AJ28,$AD$2:$AG$1120,4,0),"") | AN28: Banco Cooperativo Coopcentral | AO28: Banco Cooperativo Coopcentral | AQ28: 66 | AS28: 164 | AT28: 304 | AU28: Tratamiento de semillas para propagación | AV28: 9.66 | AX28: 0150 | AY28: Explotación mixta (agrícola y pecuaria). | BA28: Comercio al por mayor de otros tipos de maquinaria y equipo ncp, incluye el comercio al por mayor de equipo, articulos e instrumentos medicos, quirurgicos y para laboratorio, muebles, maquinaria y equipo de oficina excepto computadores y equipo periferico, instrumentos y equipo de medicion, partes, piezas y accesorios | BB28: 1465901
A29: 26 | B29: =IF('FORMATO ACTUALIZACIÓN DATOS'!F47="",0,1) -> 0 | C29: Año Contrato | D29: =IF(B29=0,CONCATENATE(" - ",C29,""),"") -> - Año Contrato | T29: BOLIVIA | U29: 097 | W29: Risaralda | X29: 66 | AB29: Antioquia | AC29: 05 | AD29: =CONCATENATE(AC29,"-",AE29) -> 05-28 | AE29: =IF(AB29=AB28,1+AE28,1) -> 28 | AF29: CAMPAMENTO | AG29: 134 | AI29: 28 | AJ29: =CONCATENATE($AA$1,"-",AI29) -> -28 | AK29: =IFERROR(VLOOKUP(AJ29,$AD$2:$AG$1120,3,0),"") | AL29: =IFERROR(VLOOKUP(AJ29,$AD$2:$AG$1120,4,0),"") | AN29: Banco Finandina S.A | AO29: Banco Finandina S.A | AQ29: 63 | AS29: 170 | AU29: Caza ordinaria y mediante trampas y actividades de servicios conexas | AV29: 0 | AX29: 0161 | AY29: Actividades de apoyo a la agricultura. | BA29: Comercio al por mayor de combustibles solidos, liquidos, gaseosos y productos conexos, incluye comercio al por mayor de grasas, lubricantes y aceites. | BB29: 1466101
A30: 27 | B30: =IF('FORMATO ACTUALIZACIÓN DATOS'!K46="",0,1) -> 0 | C30: Valor Total del Contrato | D30: =IF(B30=0,CONCATENATE(" - ",C30,""),"") -> - Valor Total del Contrato | T30: BOSNIA-HERZEGOVINA | U30: 029 | W30: Santander | X30: 68 | AB30: Antioquia | AC30: 05 | AD30: =CONCATENATE(AC30,"-",AE30) -> 05-29 | AE30: =IF(AB30=AB29,1+AE29,1) -> 29 | AF30: CAÑASGORDAS | AG30: 138 | AI30: 29 | AJ30: =CONCATENATE($AA$1,"-",AI30) -> -29 | AK30: =IFERROR(VLOOKUP(AJ30,$AD$2:$AG$1120,3,0),"") | AL30: =IFERROR(VLOOKUP(AJ30,$AD$2:$AG$1120,4,0),"") | AN30: Banco Falabella S.A | AO30: Banco Falabella S.A | AQ30: 62 | AS30: 210 | AU30: Silvicultura y otras actividades forestales | AV30: 0 | AX30: 0162 | AY30: Actividades de apoyo a la ganadería. | BA30: Comercio al por mayor de materiales de construccion, articulos de ferreteria, pinturas sin mezclado), productos de vidrio, equipo y materiales de fontaneria y calefaccion, incluye comercio al por mayor de pinturas y barnices (sin mezclado) | BB30: 1466301
A31: 28 | B31: =IF('FORMATO ACTUALIZACIÓN DATOS'!A50="",0,1) -> 0 | C31: Valor Pago Mensual según Contrato | D31: =IF(B31=0,CONCATENATE(" - ",C31,""),"") -> - Valor Pago Mensual según Contrato | K31: SI | T31: BOTSWANA | U31: 101 | W31: Sucre | X31: 70 | AB31: Antioquia | AC31: 05 | AD31: =CONCATENATE(AC31,"-",AE31) -> 05-30 | AE31: =IF(AB31=AB30,1+AE30,1) -> 30 | AF31: CARACOLÍ | AG31: 142 | AI31: 30 | AJ31: =CONCATENATE($AA$1,"-",AI31) -> -30 | AK31: =IFERROR(VLOOKUP(AJ31,$AD$2:$AG$1120,3,0),"") | AL31: =IFERROR(VLOOKUP(AJ31,$AD$2:$AG$1120,4,0),"") | AN31: Coltefinanciera S.A | AO31: Coltefinanciera S.A | AQ31: 370 | AS31: 220 | AU31: Extracción de madera | AV31: 0 | AX31: 0163 | AY31: Actividades posteriores a la cosecha. | BA31: Comercio al por mayor de productos quimicos basicos, cauchos y plasticos en formas primarias y productos quimicos de uso agropecuario, incluye materiales colorantes, plastico incluso el plastico celular (espuma), caucho en formas primarias, el comercio al por mayor de sustancias quimicas de uso industrial como: anilina, tinta de imprenta, aceites esenciales, parafina, aromas y aromatizantes, el comercio al por mayor de abonos y derivados del almidon, colorantes, resinas sinteticas | BB31: 1466401
A32: 29 | B32: =IF('FORMATO ACTUALIZACIÓN DATOS'!AC46="",0,1) -> 0 | C32: Fecha Acta de Inicio | D32: =IF(B32=0,CONCATENATE(" - ",C32,""),"") -> - Fecha Acta de Inicio | K32: NO | T32: BRASIL | U32: 105 | W32: Tolima | X32: 73 | AB32: Antioquia | AC32: 05 | AD32: =CONCATENATE(AC32,"-",AE32) -> 05-31 | AE32: =IF(AB32=AB31,1+AE31,1) -> 31 | AF32: CARAMANTA | AG32: 145 | AI32: 31 | AJ32: =CONCATENATE($AA$1,"-",AI32) -> -31 | AK32: =IFERROR(VLOOKUP(AJ32,$AD$2:$AG$1120,3,0),"") | AL32: =IFERROR(VLOOKUP(AJ32,$AD$2:$AG$1120,4,0),"") | AN32: Cooperativa Financiera de Antioquia | AO32: Cooperativa Financiera de Antioquia | AQ32: 283 | AS32: 230 | AU32: Recolección de productos forestales diferentes a la madera | AV32: 0 | AX32: 0164 | AY32: Tratamiento de semillas para propagación. | BA32: Comercio al por mayor de otros productos n.c.p., incluye el comercio al por mayor de fibras textiles, papel a granel y piedras preciosas, suministros de embalaje. | BB32: 1466901
A33: 30 | B33: =IF('FORMATO ACTUALIZACIÓN DATOS'!AN46="",0,1) -> 0 | C33: Fecha terminación Contrato | D33: =IF(B33=0,CONCATENATE(" - ",C33,""),"") -> - Fecha terminación Contrato | T33: BRUNEI DARUSSALAM | U33: 108 | W33: Valle del Cauca | X33: 76 | AB33: Antioquia | AC33: 05 | AD33: =CONCATENATE(AC33,"-",AE33) -> 05-32 | AE33: =IF(AB33=AB32,1+AE32,1) -> 32 | AF33: CAREPA | AG33: 147 | AI33: 32 | AJ33: =CONCATENATE($AA$1,"-",AI33) -> -32 | AK33: =IFERROR(VLOOKUP(AJ33,$AD$2:$AG$1120,3,0),"") | AL33: =IFERROR(VLOOKUP(AJ33,$AD$2:$AG$1120,4,0),"") | AN33: Cootrafa Cooperativa Financiera | AO33: Cootrafa Cooperativa Financiera | AQ33: 289 | AS33: 240 | AT33: 304 | AU33: Servicios de apoyo a la silvicultura | AV33: 9.66 | AX33: 0170 | AY33: Caza ordinaria y mediante trampas y actividades de servicios conexas. | BA33: Comercio al por mayor no especializado, incluye el comercio de una variedad de productos sin ninguna especializacion en particular. | BB33: 1469001
A34: 30.1 | B34: =IF('FORMATO ACTUALIZACIÓN DATOS'!V50="",0,1) -> 0 | C34: VIGENCIA FUTURA | D34: =IF(B34=0,CONCATENATE(" - ",C34,""),"") -> - VIGENCIA FUTURA | T34: BULGARIA | U34: 111 | W34: Vaupés | X34: 97 | AB34: Antioquia | AC34: 05 | AD34: =CONCATENATE(AC34,"-",AE34) -> 05-33 | AE34: =IF(AB34=AB33,1+AE33,1) -> 33 | AF34: EL CARMEN DE VIBORAL | AG34: 148 | AI34: 33 | AJ34: =CONCATENATE($AA$1,"-",AI34) -> -33 | AK34: =IFERROR(VLOOKUP(AJ34,$AD$2:$AG$1120,3,0),"") | AL34: =IFERROR(VLOOKUP(AJ34,$AD$2:$AG$1120,4,0),"") | AN34: Financiera Juriscoop S.A. Compañía Financiamiento | AO34: Financiera Juriscoop S.A. Compañía Financiamiento | AQ34: 121 | AS34: 311 | AU34: Pesca marítima | AV34: 0 | AX34: 0210 | AY34: Silvicultura y otras actividades forestales. | BA34: Comercio al por menor en establecimientos no especializados con surtido compuesto principalmente por alimentos, bebidas o tabaco, incluye establecimientos no especializados de comercio al por menor de productos cuyo surtido esta compuesto principalmente de alimentos (viveres en general) bebidas o tabaco, cosmeticos, vestuario | BB34: 1471101
A35: 31 | B35: =IF('FORMATO ACTUALIZACIÓN DATOS'!AY46="",0,1) -> 0 | C35: Cesión | D35: =IF(B35=0,CONCATENATE(" - ",C35,""),"") -> - Cesión | K35: Área Funcional de la SED | L35: CODIGO | T35: BURKINA FASSO | U35: 031 | W35: Vichada | X35: 99 | AB35: Antioquia | AC35: 05 | AD35: =CONCATENATE(AC35,"-",AE35) -> 05-34 | AE35: =IF(AB35=AB34,1+AE34,1) -> 34 | AF35: CAROLINA | AG35: 150 | AI35: 34 | AJ35: =CONCATENATE($AA$1,"-",AI35) -> -34 | AK35: =IFERROR(VLOOKUP(AJ35,$AD$2:$AG$1120,3,0),"") | AL35: =IFERROR(VLOOKUP(AJ35,$AD$2:$AG$1120,4,0),"") | AN35: Nequi | AO35: Nequi | AQ35: 507 | AS35: 312 | AU35: Pesca de agua dulce | AV35: 0 | AX35: 0220 | AY35: Extracción de madera. | BA35: Comercio al por menor en establecimientos no especializados, con surtido compuesto principalmente por alimentos, bebidas o tabaco, incluye expendio de otras mercancias para consumo de los hogares tales, electrodomesticos, muebles, articulos de ferreteria, entre otros | BB35: 1471102
A36: 32 | B36: =IF('FORMATO ACTUALIZACIÓN DATOS'!A53="",0,1) -> 0 | C36: Área Funcional de la SED | D36: =IF(B36=0,CONCATENATE(" - ",C36,""),"") -> - Área Funcional de la SED | K36: Despacho Del Secretario | L36: 1000 | T36: BURUNDI | U36: 115 | W36: Otro | AB36: Antioquia | AC36: 05 | AD36: =CONCATENATE(AC36,"-",AE36) -> 05-35 | AE36: =IF(AB36=AB35,1+AE35,1) -> 35 | AF36: CAUCASIA | AG36: 154 | AI36: 35 | AJ36: =CONCATENATE($AA$1,"-",AI36) -> -35 | AK36: =IFERROR(VLOOKUP(AJ36,$AD$2:$AG$1120,3,0),"") | AL36: =IFERROR(VLOOKUP(AJ36,$AD$2:$AG$1120,4,0),"") | AN36: Banco Multibank S.A. | AO36: Banco Multibank S.A. | AQ36: 64 | AS36: 321 | AU36: Acuicultura marítima | AV36: 0 | AX36: 0230 | AY36: Recolección de productos forestales diferentes a la madera. | BA36: Comercio al por menor en establecimientos no especializados, con surtido compuesto principalmente por productos diferentes de alimentos (viveres en general), bebidas y tabaco; incluye los establecimientos denominados bazares, cacharrerias, quincallerias, con surtido diverso de mercancias tales como cosmeticos, articulos escolares, mercerias, tarjetas, jugueteria, fantasias, entre otros | BB36: 1471901
A37: 33 | B37: =IF('FORMATO ACTUALIZACIÓN DATOS'!J53="",0,1) -> 0 | C37: Nombre Interventor Contrato | D37: =IF(B37=0,CONCATENATE(" - ",C37,""),"") -> - Nombre Interventor Contrato | K37: Oficina Asesora de Planeación | L37: 1100 | T37: BUTAN | U37: 119 | AB37: Antioquia | AC37: 05 | AD37: =CONCATENATE(AC37,"-",AE37) -> 05-36 | AE37: =IF(AB37=AB36,1+AE36,1) -> 36 | AF37: CHIGORODÓ | AG37: 172 | AI37: 36 | AJ37: =CONCATENATE($AA$1,"-",AI37) -> -36 | AK37: =IFERROR(VLOOKUP(AJ37,$AD$2:$AG$1120,3,0),"") | AL37: =IFERROR(VLOOKUP(AJ37,$AD$2:$AG$1120,4,0),"") | AN37: Banco Serfinanza S.A | AO37: Banco Serfinanza S.A | AQ37: 69 | AS37: 322 | AU37: Acuicultura de agua dulce | AV37: 0 | AX37: 0240 | AY37: Servicios de apoyo a la silvicultura. | BA37: Comercio al por menor de leche, productos lacteos y huevos en establecimientos especializados, incluye comercio al por menor de leche, productos lacteos (mantequilla, quesos, cuajadas, cremas de leche, yogur) y huevos, sin autotransporte | BB37: 1472201
A38: 34 | B38: =IF('FORMATO ACTUALIZACIÓN DATOS'!S53="",0,1) -> 0 | C38: Cargo Interventor Contrato | D38: =IF(B38=0,CONCATENATE(" - ",C38,""),"") -> - Cargo Interventor Contrato | K38: Oficina de Control Interno | L38: 1200 | T38: CABO VERDE | U38: 127 | AB38: Antioquia | AC38: 05 | AD38: =CONCATENATE(AC38,"-",AE38) -> 05-37 | AE38: =IF(AB38=AB37,1+AE37,1) -> 37 | AF38: CISNEROS | AG38: 190 | AI38: 37 | AJ38: =CONCATENATE($AA$1,"-",AI38) -> -37 | AK38: =IFERROR(VLOOKUP(AJ38,$AD$2:$AG$1120,3,0),"") | AL38: =IFERROR(VLOOKUP(AJ38,$AD$2:$AG$1120,4,0),"") | AN38: Citibank NA | AO38: Citibank NA | AQ38: 995 | AS38: 510 | AT38: 103 | AU38: Extracción de hulla (carbón de piedra) | AV38: 11.04 | AX38: 0311 | AY38: Pesca marítima. | BA38: Comercio al por menor de carnes (incluye aves de corral), productos carnicos, pescado fresco, preparado o en conserva, mariscos y productos de mar, en establecimientos especializados, incluye venta de productos carnicos y de salsamentaria | BB38: 1472301
A39: 35 | B39: =IF('FORMATO ACTUALIZACIÓN DATOS'!Z53="",0,1) -> 0 | C39: Nombre Operativo | D39: =IF(B39=0,CONCATENATE(" - ",C39,""),"") -> - Nombre Operativo | K39: Oficina Asesora JurIdica | L39: 1300 | T39: CAIMAN, ISLAS | U39: 137 | AB39: Antioquia | AC39: 05 | AD39: =CONCATENATE(AC39,"-",AE39) -> 05-38 | AE39: =IF(AB39=AB38,1+AE38,1) -> 38 | AF39: COCORNÁ | AG39: 197 | AI39: 38 | AJ39: =CONCATENATE($AA$1,"-",AI39) -> -38 | AK39: =IFERROR(VLOOKUP(AJ39,$AD$2:$AG$1120,3,0),"") | AL39: =IFERROR(VLOOKUP(AJ39,$AD$2:$AG$1120,4,0),"") | AN39: Standard Chartered Bank | AO39: Standard Chartered Bank | AQ39: 996 | AS39: 520 | AT39: 103 | AU39: Extracción de carbón lignito | AV39: 11.04 | AX39: 0312 | AY39: Pesca de agua dulce. | BA39: Comercio al por menor de bebidas y productos del tabaco en establecimientos especializados, incluye cigarrerias y establecimientos especializados de bebidas alcoholicas y no alcoholicas para ser consumidas fuera del lugar de venta, el surtido de estos establecimientos esta constituido principalmente por cervezas, aguardiente, vinos, champañas, aguas minerales naturales, gaseosas, jugos de fruta, entre otros. | BB39: 1472401
A40: 36 | B40: =IF('FORMATO ACTUALIZACIÓN DATOS'!AH53="",0,1) -> 0 | C40: Identificación Operativo | D40: =IF(B40=0,CONCATENATE(" - ",C40,""),"") -> - Identificación Operativo | K40: Oficina de Control Disciplinario de Instrucción | L40: 1400 | T40: CAMERUN, REPUBLICA U | U40: 145 | AB40: Antioquia | AC40: 05 | AD40: =CONCATENATE(AC40,"-",AE40) -> 05-39 | AE40: =IF(AB40=AB39,1+AE39,1) -> 39 | AF40: CONCEPCIÓN | AG40: 206 | AI40: 39 | AJ40: =CONCATENATE($AA$1,"-",AI40) -> -39 | AK40: =IFERROR(VLOOKUP(AJ40,$AD$2:$AG$1120,3,0),"") | AL40: =IFERROR(VLOOKUP(AJ40,$AD$2:$AG$1120,4,0),"") | AN40: Banco Davivienda S.A -DAVIPLATA | AO40: Banco Davivienda S.A -DAVIPLATA | AQ40: 551 | AS40: 610 | AT40: 103 | AU40: Extracción de petróleo crudo | AV40: 11.04 | AX40: 0321 | AY40: Acuicultura marítima. | BA40: Comercio al por menor de bebidas y productos del tabaco en establecimientos especializados, incluye comercio al por menor de productos de tabaco tales como cigarros, cigarrillos, picaduras, tabaco para mascar y rape y de hielo, helados y refrescos. | BB40: 1472402
A41: 37 | B41: =IF('FORMATO ACTUALIZACIÓN DATOS'!AX50="",0,1) -> 0 | C41: Codigo ARL | D41: =IF(B41=0,CONCATENATE(" - ",C41,""),"") -> - Codigo ARL | K41: Oficina de Control Disciplinario de Juzgamiento | L41: 1500 | T41: CANADA | U41: 149 | AB41: Antioquia | AC41: 05 | AD41: =CONCATENATE(AC41,"-",AE41) -> 05-40 | AE41: =IF(AB41=AB40,1+AE40,1) -> 40 | AF41: CONCORDIA | AG41: 209 | AI41: 40 | AJ41: =CONCATENATE($AA$1,"-",AI41) -> -40 | AK41: =IFERROR(VLOOKUP(AJ41,$AD$2:$AG$1120,3,0),"") | AL41: =IFERROR(VLOOKUP(AJ41,$AD$2:$AG$1120,4,0),"") | AN41: JP MORGAN CHASE N.Y. | AO41: JP MORGAN CHASE N.Y. | AQ41: 151 | AS41: 620 | AT41: 103 | AU41: Extracción de gas natural | AV41: 11.04 | AX41: 0322 | AY41: Acuicultura de agua dulce. | BA41: Comercio al por menor de otros productos alimenticios ncp, en establecimientos especializados, incluye leche en polvo, miel natural, avena en hojuelas, sal comun, cafe, te, azucar, cacao, especias, entre otros; confiteria o dulceria, preparados principalmente con azucar, frutas, nueces secas confitadas, gomas de mascar, caramelos, turrones, jaleas, bocadillos, entre otros | BB41: 1472901
A42: 38 | B42: =IF('FORMATO ACTUALIZACIÓN DATOS'!AA11=1,1,IF(G42=1,1,0)) -> 0 | C42: Pregunta C1 | D42: =IF(B42=0,CONCATENATE(" - ",C42,""),"") -> - Pregunta C1 | E42: =IF('FORMATO ACTUALIZACIÓN DATOS'!BA61="X",1,0) -> 0 | F42: =IF('FORMATO ACTUALIZACIÓN DATOS'!BC61="X",1,0) -> 0 | G42: =SUM(E42:F42) -> 0 | K42: Oficina Asesora de Comunicación y Prensa | L42: 1600 | T42: CANAL(NORMANDAS),ISL | U42: 155 | AB42: Antioquia | AC42: 05 | AD42: =CONCATENATE(AC42,"-",AE42) -> 05-41 | AE42: =IF(AB42=AB41,1+AE41,1) -> 41 | AF42: COPACABANA | AG42: 212 | AI42: 41 | AJ42: =CONCATENATE($AA$1,"-",AI42) -> -41 | AK42: =IFERROR(VLOOKUP(AJ42,$AD$2:$AG$1120,3,0),"") | AL42: =IFERROR(VLOOKUP(AJ42,$AD$2:$AG$1120,4,0),"") | AN42: HSBC MÉXICO, S.A. | AO42: HSBC MÉXICO, S.A. | AQ42: 994 | AS42: 710 | AT42: 103 | AU42: Extracción de minerales de hierro | AV42: 11.04 | AX42: 0510 | AY42: Extracción de hulla (carbón de piedra). | BA42: Comercio al por menor de otros productos alimenticios ncp, en establecimientos especializados, incluye aceites y grasas animales y vegetales, almidones, productos farinaceos, productos de panaderia | BB42: 1472902
A43: 39 | B43: =IF('FORMATO ACTUALIZACIÓN DATOS'!AA11=1,1,IF(G43=1,1,0)) -> 0 | C43: Pregunta C2 | D43: =IF(B43=0,CONCATENATE(" - ",C43,""),"") -> - Pregunta C2 | E43: =IF('FORMATO ACTUALIZACIÓN DATOS'!BA64="X",1,0) -> 0 | F43: =IF('FORMATO ACTUALIZACIÓN DATOS'!BC64="X",1,0) -> 0 | G43: =SUM(E43:F43) -> 0 | K43: Oficina de TecnologÍas de la Información y las Comunicaciones | L43: 1700 | T43: CANTON ENDERBURY,ISL | U43: 157 | AB43: Antioquia | AC43: 05 | AD43: =CONCATENATE(AC43,"-",AE43) -> 05-42 | AE43: =IF(AB43=AB42,1+AE42,1) -> 42 | AF43: DABEIBA | AG43: 234 | AI43: 42 | AJ43: =CONCATENATE($AA$1,"-",AI43) -> -42 | AK43: =IFERROR(VLOOKUP(AJ43,$AD$2:$AG$1120,3,0),"") | AL43: =IFERROR(VLOOKUP(AJ43,$AD$2:$AG$1120,4,0),"") | AN43: Bank of America N.A | AO43: Bank of America N.A | AQ43: 993 | AS43: 721 | AT43: 103 | AU43: Extracción de minerales de uranio y de torio | AV43: 11.04 | AX43: 0520 | AY43: Extracción de carbón lignito. | BA43: Comercio al por menor de lubricantes (aceites, grasas), aditivos y productos de limpieza para vehiculos automotores, incluye: comercio al por menor de todo tipo de lubricantes, aditivos, refrigerantes y productos de limpieza para vehiculos automotores, motocicletas, trineos motorizados y embarcaciones | BB43: 1473201
A44: 40 | B44: =IF('FORMATO ACTUALIZACIÓN DATOS'!AA13=1,1,IF(G44=1,1,0)) -> 0 | C44: Pregunta C3 | D44: =IF(B44=0,CONCATENATE(" - ",C44,""),"") -> - Pregunta C3 | E44: =IF('FORMATO ACTUALIZACIÓN DATOS'!BA67="X",1,0) -> 0 | F44: =IF('FORMATO ACTUALIZACIÓN DATOS'!BC67="X",1,0) -> 0 | G44: =SUM(E44:F44) -> 0 | K44: Oficina para la Convivencia Escolar | L44: 1800 | T44: CHAD | U44: 203 | AB44: Antioquia | AC44: 05 | AD44: =CONCATENATE(AC44,"-",AE44) -> 05-43 | AE44: =IF(AB44=AB43,1+AE43,1) -> 43 | AF44: DON MATÍAS | AG44: 237 | AI44: 43 | AJ44: =CONCATENATE($AA$1,"-",AI44) -> -43 | AK44: =IFERROR(VLOOKUP(AJ44,$AD$2:$AG$1120,3,0),"") | AL44: =IFERROR(VLOOKUP(AJ44,$AD$2:$AG$1120,4,0),"") | AN44: SUNTRUST BANK | AO44: SUNTRUST BANK | AQ44: 992 | AS44: 722 | AT44: 103 | AU44: Extracción de oro y otros metales preciosos | AV44: 11.04 | AX44: 0610 | AY44: Extracción de petróleo crudo. | BA44: Comercio al por menor de computadores, equipos perifericos, programas de informatica y equipos de telecomunicaciones en establecimientos especializados, incluye comercio al por menor de computadores, equipo periferico, consolas de videojuegos, programas de informatica no personalizados y de equipos de telecomunicaciones, como telefonos celulares, buscapersonas etc | BB44: 1474101
A45: 41 | B45: =IF('FORMATO ACTUALIZACIÓN DATOS'!AA11=1,1,IF(G45=1,1,0)) -> 0 | C45: Pregunta C4 | D45: =IF(B45=0,CONCATENATE(" - ",C45,""),"") -> - Pregunta C4 | E45: =IF('FORMATO ACTUALIZACIÓN DATOS'!BA70="X",1,0) -> 0 | F45: =IF('FORMATO ACTUALIZACIÓN DATOS'!BC70="X",1,0) -> 0 | G45: =SUM(E45:F45) -> 0 | K45: Subsecretaría De Integración Interinstitucional | L45: 2000 | T45: CHILE | U45: 211 | AB45: Antioquia | AC45: 05 | AD45: =CONCATENATE(AC45,"-",AE45) -> 05-44 | AE45: =IF(AB45=AB44,1+AE44,1) -> 44 | AF45: EBÉJICO | AG45: 240 | AI45: 44 | AJ45: =CONCATENATE($AA$1,"-",AI45) -> -44 | AK45: =IFERROR(VLOOKUP(AJ45,$AD$2:$AG$1120,3,0),"") | AL45: =IFERROR(VLOOKUP(AJ45,$AD$2:$AG$1120,4,0),"") | AN45: Banco Mundo Mujer | AO45: Banco Mundo Mujer | AQ45: 47 | AS45: 723 | AT45: 103 | AU45: Extracción de minerales de níquel | AV45: 11.04 | AX45: 0620 | AY45: Extracción de gas natural. | BA45: Comercio al por menor de equipos y aparatos de sonido y de video en establecimientos especializados, incluye comercio al por menor de equipos radio y television, equipo estereofonico y aparatos de reproduccion y de grabacion de CD, DVD, Blu-ray Disc; demas dispositivos de almacenamiento y reproduccion de audio y de video; de microfonos, amplificadores, parlantes, consolas, entre otros | BB45: 1474201
A46: 42 | B46: =IF(G46=0,0,IF('FORMATO ACTUALIZACIÓN DATOS'!AA11=1,1,IF(E46=0,1,IF('FORMATO ACTUALIZACIÓN DATOS'!I83="",0,1)))) -> 0 | C46: Entidad (AFC) | D46: =IF(B46=0,CONCATENATE(" - ",C46,""),"") -> - Entidad (AFC) | E46: =IF('FORMATO ACTUALIZACIÓN DATOS'!S82="X",1,0) -> 0 | F46: =IF('FORMATO ACTUALIZACIÓN DATOS'!V82="X",1,0) -> 0 | G46: =SUM(E46:F46) -> 0 | K46: Dirección General de Educación y Colegios Distritales (DILES) | L46: 2100 | T46: CHINA | U46: 215 | AB46: Antioquia | AC46: 05 | AD46: =CONCATENATE(AC46,"-",AE46) -> 05-45 | AE46: =IF(AB46=AB45,1+AE45,1) -> 45 | AF46: EL BAGRE | AG46: 250 | AI46: 45 | AJ46: =CONCATENATE($AA$1,"-",AI46) -> -45 | AK46: =IFERROR(VLOOKUP(AJ46,$AD$2:$AG$1120,3,0),"") | AL46: =IFERROR(VLOOKUP(AJ46,$AD$2:$AG$1120,4,0),"") | AN46: FÉDÉRATION DES CAISSES DESJARDINS DU QUÉBEC | AO46: FÉDÉRATION DES CAISSES DESJARDINS DU QUÉBEC | AQ46: 989 | AS46: 729 | AT46: 103 | AU46: Extracción de otros minerales metalíferos no ferrosos n.c.p. | AV46: 11.04 | AX46: 0710 | AY46: Extracción de minerales de hierro. | BA46: Comercio al por menor de productos textiles en establecimientos especializados, incluye el comercio de lana (y de otros hilados para tejer y bordar), tejidos de fibras textiles, afelpados y telas en general elaboradas con fibras naturales, artificiales y sinteticas., de merceria: agujas, hilo para coser, cintas, encajes ente otros. | BB46: 1475101
A47: 43 | B47: =IF(G46=0,0,IF('FORMATO ACTUALIZACIÓN DATOS'!AA11=1,1,IF(E46=0,1,IF('FORMATO ACTUALIZACIÓN DATOS'!I84="",0,1)))) -> 0 | C47: NIT (AFC) | D47: =IF(B47=0,CONCATENATE(" - ",C47,""),"") -> - NIT (AFC) | K47: Dirección de Participación y Relaciones Interinstitucionales | L47: 2300 | T47: CHIPRE | U47: 221 | AB47: Antioquia | AC47: 05 | AD47: =CONCATENATE(AC47,"-",AE47) -> 05-46 | AE47: =IF(AB47=AB46,1+AE46,1) -> 46 | AF47: ENTRERRIOS | AG47: 264 | AI47: 46 | AJ47: =CONCATENATE($AA$1,"-",AI47) -> -46 | AK47: =IFERROR(VLOOKUP(AJ47,$AD$2:$AG$1120,3,0),"") | AL47: =IFERROR(VLOOKUP(AJ47,$AD$2:$AG$1120,4,0),"") | AN47: Deutsche Bank Trust Company Americas | AO47: Deutsche Bank Trust Company Americas | AQ47: 991 | AS47: 811 | AT47: 103 | AU47: Extracción de piedra, arena, arcillas comunes, yeso y anhidrita | AV47: 11.04 | AX47: 0721 | AY47: Extracción de minerales de uranio y de torio. | BA47: Comercio al por menor de articulos de ferreteria, pinturas, barnices, lacas, vinilos, masillas, esmaltes, pigmentos y productos de vidrio en establecimientos especializados, incluye material y equipo de bricolaje o maquinaria ligera e implementos para industria en general | BB47: 1475201
A48: 44 | B48: =IF(G46=0,0,IF('FORMATO ACTUALIZACIÓN DATOS'!AA11=1,1,IF(E46=0,1,IF('FORMATO ACTUALIZACIÓN DATOS'!I85="",0,1)))) -> 0 | C48: Valor Mensual (AFC) | D48: =IF(B48=0,CONCATENATE(" - ",C48,""),"") -> - Valor Mensual (AFC) | K48: Dirección de Relaciones con el Sector Educativo Privado | L48: 2400 | T48: CIUDAD DEL VATICANO | U48: 159 | AB48: Antioquia | AC48: 05 | AD48: =CONCATENATE(AC48,"-",AE48) -> 05-47 | AE48: =IF(AB48=AB47,1+AE47,1) -> 47 | AF48: ENVIGADO | AG48: 266 | AI48: 47 | AJ48: =CONCATENATE($AA$1,"-",AI48) -> -47 | AK48: =IFERROR(VLOOKUP(AJ48,$AD$2:$AG$1120,3,0),"") | AL48: =IFERROR(VLOOKUP(AJ48,$AD$2:$AG$1120,4,0),"") | AN48: DUMY1 | AO48: DUMY1 | AQ48: 1 | AS48: 812 | AT48: 103 | AU48: Extracción de arcillas de uso industrial, caliza, caolín y bentonitas | AV48: 11.04 | AX48: 0722 | AY48: Extracción de oro y otros metales preciosos. | BA48: Comercio al por menor de articulos de ferreteria, pinturas, barnices, lacas, vinilos, masillas, esmaltes, pigmentos y productos de vidrio en establecimientos especializados, incluye comercio al por menor de pinturas, | BB48: 1475202
A49: 45 | B49: =IF(G49=0,0,IF('FORMATO ACTUALIZACIÓN DATOS'!AA11=1,1,IF(F49=1,1,IF('FORMATO ACTUALIZACIÓN DATOS'!AN83="",0,1)))) -> 0 | C49: Entidad (Pensiones Voluntarias) | D49: =IF(B49=0,CONCATENATE(" - ",C49,""),"") -> - Entidad (Pensiones Voluntarias) | E49: =IF('FORMATO ACTUALIZACIÓN DATOS'!AX82="X",1,0) -> 0 | F49: =IF('FORMATO ACTUALIZACIÓN DATOS'!BA82="X",1,0) -> 0 | G49: =E49+F49 -> 0 | K49: Dirección de Inspección y Vigilancia | L49: 2500 | T49: COCOS (KEELING), ISL | U49: 165 | AB49: Antioquia | AC49: 05 | AD49: =CONCATENATE(AC49,"-",AE49) -> 05-48 | AE49: =IF(AB49=AB48,1+AE48,1) -> 48 | AF49: FREDONIA | AG49: 282 | AI49: 48 | AJ49: =CONCATENATE($AA$1,"-",AI49) -> -48 | AK49: =IFERROR(VLOOKUP(AJ49,$AD$2:$AG$1120,3,0),"") | AL49: =IFERROR(VLOOKUP(AJ49,$AD$2:$AG$1120,4,0),"") | AN49: JP MORGAN CHASE BANK | AO49: JP MORGAN CHASE BANK | AQ49: 988 | AS49: 820 | AT49: 103 | AU49: Extracción de esmeraldas, piedras preciosas y semipreciosas | AV49: 11.04 | AX49: 0723 | AY49: Extracción de minerales de níquel. | BA49: Comercio al por menor de tapices, alfombras y cubrimientos para paredes y pisos en establecimientos especializados, incluye comercio de tapices, alfombras y persianas, papel para empapelar y recubrimientos para pisos | BB49: 1475301
A50: 46 | B50: =IF(G49=0,0,IF('FORMATO ACTUALIZACIÓN DATOS'!AA11=1,1,IF(E49=0,1,IF('FORMATO ACTUALIZACIÓN DATOS'!AN84="",0,1)))) -> 0 | C50: NIT (Pensiones Voluntarias) | D50: =IF(B50=0,CONCATENATE(" - ",C50,""),"") -> - NIT (Pensiones Voluntarias) | K50: Dir. de Relac con los Sect de Educa Superior y Educa para el Trabajo | L50: 2600 | T50: COLOMBIA | U50: 169 | AB50: Antioquia | AC50: 05 | AD50: =CONCATENATE(AC50,"-",AE50) -> 05-49 | AE50: =IF(AB50=AB49,1+AE49,1) -> 49 | AF50: FRONTINO | AG50: 284 | AI50: 49 | AJ50: =CONCATENATE($AA$1,"-",AI50) -> -49 | AK50: =IFERROR(VLOOKUP(AJ50,$AD$2:$AG$1120,3,0),"") | AL50: =IFERROR(VLOOKUP(AJ50,$AD$2:$AG$1120,4,0),"") | AN50: BANCO DUMMY MULTAS SED | AO50: BANCO DUMMY MULTAS SED | AQ50: 994 | AS50: 891 | AT50: 103 | AU50: Extracción de minerales para la fabricación de abonos y productos químicos | AV50: 11.04 | AX50: 0729 | AY50: Extracción de otros minerales metalíferos no ferrosos n.c.p. | BA50: Comercio al por menor de electrodomesticos y gas domestico de uso domestico; muebles y equipos de iluminacion, incluye comercio al por menor de muebles, articulos de iluminacion y todo tipo de electrodomesticos y gasodomesticos: refrigeradores, lavadoras, maquinas para secar ropa, lavaplatos, aspiradoras, aparatos para calefaccion, hornos, asadores, estufas, calentadores, entre otros | BB50: 1475401
A51: 47 | B51: =IF(G49=0,0,IF('FORMATO ACTUALIZACIÓN DATOS'!AA11=1,1,IF(E49=0,1,IF('FORMATO ACTUALIZACIÓN DATOS'!AN85>0,1,0)))) -> 0 | C51: Valor Mensual (Pensiones Voluntarias) | D51: =IF(B51=0,CONCATENATE(" - ",C51,""),"") -> - Valor Mensual (Pensiones Voluntarias) | K51: DIRECCIONES LOCALES DE EDUCACION | L51: 2200 | T51: COMORAS | U51: 173 | AB51: Antioquia | AC51: 05 | AD51: =CONCATENATE(AC51,"-",AE51) -> 05-50 | AE51: =IF(AB51=AB50,1+AE50,1) -> 50 | AF51: GIRALDO | AG51: 306 | AI51: 50 | AJ51: =CONCATENATE($AA$1,"-",AI51) -> -50 | AK51: =IFERROR(VLOOKUP(AJ51,$AD$2:$AG$1120,3,0),"") | AL51: =IFERROR(VLOOKUP(AJ51,$AD$2:$AG$1120,4,0),"") | AN51: BANCO BILBAO VIZCAYA ARGENTARIA S.A. (ESPAÑA) | AO51: BANCO BILBAO VIZCAYA ARGENTARIA S.A. (ESPAÑA) | AQ51: 182 | AS51: 892 | AT51: 103 | AU51: Extracción de halita (sal) | AV51: 11.04 | AX51: 0811 | AY51: Extracción de piedra, arena, arcillas comunes, yeso y anhidrita. | BA51: Comercio al por menor de articulos y utensilios de uso domestico, incluye el comercio de cubiertos, vajilla, cristaleria, y objetos de porcelana y de ceramica; productos de madera corcho y mimbre, instrumentos musicales y partituras; lenceria y todo tipo de confecciones para el hogar elaboradas en materiales textiles; ropa de cama, manteleria, toallas de baño, paños de cocina, cortinas, visillos, frazadas, cobertores, acolchados, etc, y otros articulos de uso domestico | BB51: 1475501
A52: 48 | B52: =IF('FORMATO ACTUALIZACIÓN DATOS'!N50="",0,1) -> 0 | C52: Número CRP | D52: =IF(B52=0,CONCATENATE(" - ",C52,""),"") -> - Número CRP | K52: Subsecretaría De Calidad Y Pertinencia | L52: 3000 | T52: COMUNIDAD EUROPEA | U52: 998 | AB52: Antioquia | AC52: 05 | AD52: =CONCATENATE(AC52,"-",AE52) -> 05-51 | AE52: =IF(AB52=AB51,1+AE51,1) -> 51 | AF52: GIRARDOTA | AG52: 308 | AI52: 51 | AJ52: =CONCATENATE($AA$1,"-",AI52) -> -51 | AK52: =IFERROR(VLOOKUP(AJ52,$AD$2:$AG$1120,3,0),"") | AL52: =IFERROR(VLOOKUP(AJ52,$AD$2:$AG$1120,4,0),"") | AN52: BANCOLOMBIA PANAMÁ | AO52: BANCOLOMBIA PANAMÁ | AQ52: 996 | AS52: 899 | AT52: 103 | AU52: Extracción de otros minerales no metálicos n.c.p. | AV52: 11.04 | AX52: 0812 | AY52: Extracción de arcillas de uso industrial, caliza, caolín y bentonitas. | BA52: Comercio al por menor de otros articulos domesticos en establecimientos especializados, incluye comercio de enseres y aparatos de uso domestico ncp, recuerdos, artesanias y articulos religiosos incluso velas, sistemas de seguridad como dispositivos de cierre, cajas de caudales y cajas fuertes sin servicio de monitoreo, preparados para perfumar o desodorizar ambientes, preparados para limpiar y pulir como detergentes y preparados para lavar, betunes, lustres y cremas para calzado, lustres y cremas para muebles, pisos y otros usos, comercio de paraguas, el comercio de monedas, billetes y estampillas de coleccion, de extintores | BB52: 1475901
A53: 49 | B53: =IF('FORMATO ACTUALIZACIÓN DATOS'!Q50="",0,1) -> 0 | C53: Fecha del CRP | D53: =IF(B53=0,CONCATENATE(" - ",C53,""),"") -> - Fecha del CRP | K53: Dirección de Educación Preescolar y Básica | L53: 3100 | T53: CONGO | U53: 177 | AB53: Antioquia | AC53: 05 | AD53: =CONCATENATE(AC53,"-",AE53) -> 05-52 | AE53: =IF(AB53=AB52,1+AE52,1) -> 52 | AF53: GÓMEZ PLATA | AG53: 310 | AI53: 52 | AJ53: =CONCATENATE($AA$1,"-",AI53) -> -52 | AK53: =IFERROR(VLOOKUP(AJ53,$AD$2:$AG$1120,3,0),"") | AL53: =IFERROR(VLOOKUP(AJ53,$AD$2:$AG$1120,4,0),"") | AN53: CAPITAL ONE BANK | AO53: CAPITAL ONE BANK | AQ53: 989 | AS53: 910 | AT53: 304 | AU53: Actividades de apoyo para la extracción de petróleo y de gas natural | AV53: 9.66 | AX53: 0820 | AY53: Extracción de esmeraldas, piedras preciosas y semipreciosas. | BA53: Comercio al por menor de otros articulos domesticos en establecimientos especializados, incluye comercio de animales domesticos y alimentos concentrados para los mismos, en establecimientos Ademas, incluye las actividades propias de las tiendas que comercializan accesorios y suministros para mascotas | BB53: 1475902
A54: 50 | B54: =E54+F54 -> 1 | C54: ='FORMATO ACTUALIZACIÓN DATOS'!D80 -> 0 | D54: =IF('FORMATO DEDUCCIONES'!B25<>"","",IF(E54=0,CONCATENATE(" - ","Diligencie el formato deducciones por dependientes",""),"")) | E54: =IF(C54="FORMATO SED - CON ANEXOS",0,1) -> 1 | F54: =IF('FORMATO DEDUCCIONES'!B25<>"",1,0) -> 0 | K54: Dirección de Educación Media | L54: 3200 | T54: COOK, ISLAS | U54: 183 | AB54: Antioquia | AC54: 05 | AD54: =CONCATENATE(AC54,"-",AE54) -> 05-53 | AE54: =IF(AB54=AB53,1+AE53,1) -> 53 | AF54: GRANADA | AG54: 313 | AI54: 53 | AJ54: =CONCATENATE($AA$1,"-",AI54) -> -53 | AK54: =IFERROR(VLOOKUP(AJ54,$AD$2:$AG$1120,3,0),"") | AL54: =IFERROR(VLOOKUP(AJ54,$AD$2:$AG$1120,4,0),"") | AN54: BANCOLOMBIA PANAMA MONEY MARKET | AO54: BANCOLOMBIA PANAMA MONEY MARKET | AQ54: 985 | AS54: 990 | AT54: 304 | AU54: Actividades de apoyo para otras actividades de explotación de minas y canteras | AV54: 9.66 | AX54: 0891 | AY54: Extracción de minerales para la fabricación de abonos y productos químicos. | BA54: Comercio al por menor de libros, periodicos, materiales y articulos de papeleria y escritorio en establecimientos especializados, incluye comercio al por menor de libros, revistas, periodicos y articulos de filatelia, papeleria, utiles escolares y de escritorio, distintos de los de uso especifico en oficina. | BB54: 1476101
A55: 51 | B55: =E55+F55 -> 1 | C55: ='FORMATO ACTUALIZACIÓN DATOS'!M80 -> 0 | D55: =IF('FORMATO DEDUCCIONES'!H46<>"","",IF(E55=0,CONCATENATE(" - ","Diligencie el formato deducciones por credito hipotecario",""),"")) | E55: =IF(C55="FORMATO SED - CON ANEXOS",0,1) -> 1 | F55: =IF('FORMATO DEDUCCIONES'!H46<>"",1,0) -> 0 | K55: Dirección de Ciencias, TecnologIas y Medios Educativos | L55: 3300 | T55: COREA DEL NORTE,REPU | U55: 187 | AB55: Antioquia | AC55: 05 | AD55: =CONCATENATE(AC55,"-",AE55) -> 05-54 | AE55: =IF(AB55=AB54,1+AE54,1) -> 54 | AF55: GUADALUPE | AG55: 315 | AI55: 54 | AJ55: =CONCATENATE($AA$1,"-",AI55) -> -54 | AK55: =IFERROR(VLOOKUP(AJ55,$AD$2:$AG$1120,3,0),"") | AL55: =IFERROR(VLOOKUP(AJ55,$AD$2:$AG$1120,4,0),"") | AN55: BANQUE & CAISSE EPARGNE ETAT | AO55: BANQUE & CAISSE EPARGNE ETAT | AQ55: 986 | AS55: 1011 | AT55: 101 | AU55: Procesamiento y conservación de carne y productos cárnicos | AV55: 4.14 | AX55: 0892 | AY55: Extracción de halita (sal). | BA55: Comercio al por menor de articulos deportivos en establecimientos especializados; incluye comercio al por menor de bicicletas, patines, monopatines, cañas de pescar, articulos para acampar, botes y demas articulos deportivos en general | BB55: 1476201
A56: 52 | B56: =E56+F56 -> 1 | C56: ='FORMATO ACTUALIZACIÓN DATOS'!V80 -> 0 | D56: =IF('FORMATO DEDUCCIONES'!H35<>"","",IF(E56=0,CONCATENATE(" - ","Diligencie el formato No Pos",""),"")) | E56: =IF(C56="FORMATO SED - CON ANEXOS",0,1) -> 1 | F56: =IF('FORMATO DEDUCCIONES'!H35<>"",1,0) -> 0 | K56: Dirección de Inclusión e Integración de Poblaciones | L56: 3400 | T56: COREA DEL SUR, REPUB | U56: 190 | AB56: Antioquia | AC56: 05 | AD56: =CONCATENATE(AC56,"-",AE56) -> 05-55 | AE56: =IF(AB56=AB55,1+AE55,1) -> 55 | AF56: GUARNE | AG56: 318 | AI56: 55 | AJ56: =CONCATENATE($AA$1,"-",AI56) -> -55 | AK56: =IFERROR(VLOOKUP(AJ56,$AD$2:$AG$1120,3,0),"") | AL56: =IFERROR(VLOOKUP(AJ56,$AD$2:$AG$1120,4,0),"") | AN56: MOVII | AO56: MOVII | AQ56: 801 | AS56: 1012 | AT56: 101 | AU56: Procesamiento y conservación de pescados, crustáceos y moluscos | AV56: 4.14 | AX56: 0899 | AY56: Extracción de otros minerales no metálicos n.c.p. | BA56: Comercio al por menor de otros articulos culturales y de entretenimiento ncp en establecimientos especializados, incluye el comercio de: discos compactos, casetes de musica, cintas de video y DVD, Blu-ray Disc y demas dispositivos de almacenamiento de audio y de video juegos, juguetes, articulos de piñateria y materiales para manualidades artisticas | BB56: 1476901
B57: =IFERROR(SUM(B3:B56),0) -> 5 | K57: Dirección de Formación de Docentes e Innovaciones Pedagógicas | L57: 3500 | T57: COSTA DE MARFIL | U57: 193 | AB57: Antioquia | AC57: 05 | AD57: =CONCATENATE(AC57,"-",AE57) -> 05-56 | AE57: =IF(AB57=AB56,1+AE56,1) -> 56 | AF57: GUATAPE | AG57: 321 | AI57: 56 | AJ57: =CONCATENATE($AA$1,"-",AI57) -> -56 | AK57: =IFERROR(VLOOKUP(AJ57,$AD$2:$AG$1120,3,0),"") | AL57: =IFERROR(VLOOKUP(AJ57,$AD$2:$AG$1120,4,0),"") | AN57: POWWI | AO57: POWWI | AQ57: 803 | AS57: 1030 | AT57: 101 | AU57: Elaboración de aceites y grasas de origen vegetal y animal | AV57: 4.14 | AX57: 0910 | AY57: Actividades de apoyo para la extracción de petróleo y de gas natural. | BA57: Comercio al por menor de prendas de vestir y sus accesorios (incluye articulos de piel) en establecimientos especializados, incluye comercio al por menor de prendas de vestir como guantes, corbatas, tirantes, etcetera, articulos de piel, accesorios de vestir y ropa deportiva | BB57: 1477101
K58: Dirección de Evaluación de la Educación | L58: 3600 | T58: COSTA RICA | U58: 196 | AB58: Antioquia | AC58: 05 | AD58: =CONCATENATE(AC58,"-",AE58) -> 05-57 | AE58: =IF(AB58=AB57,1+AE57,1) -> 57 | AF58: HELICONIA | AG58: 347 | AI58: 57 | AJ58: =CONCATENATE($AA$1,"-",AI58) -> -57 | AK58: =IFERROR(VLOOKUP(AJ58,$AD$2:$AG$1120,3,0),"") | AL58: =IFERROR(VLOOKUP(AJ58,$AD$2:$AG$1120,4,0),"") | AN58: DALE | AO58: DALE | AQ58: 97 | AS58: 1051 | AT58: 101 | AU58: Elaboración de productos de molinería | AV58: 4.14 | AX58: 0990 | AY58: Actividades de apoyo para otras actividades de explotación de minas y canteras. | BA58: Comercio al por menor de todo tipo de calzado y articulos de cuero y sucedaneos del cuero en establecimientos especializados, incluye el comercio de calzados, articulos de cuero y accesorios de viaje de cuero natural y cuero artificial o de imitacion, zapatos deportivos. | BB58: 1477201
K59: Subsecretaría De Acceso y Permanencia | L59: 4000 | T59: CROACIA | U59: 198 | AB59: Antioquia | AC59: 05 | AD59: =CONCATENATE(AC59,"-",AE59) -> 05-58 | AE59: =IF(AB59=AB58,1+AE58,1) -> 58 | AF59: HISPANIA | AG59: 353 | AI59: 58 | AJ59: =CONCATENATE($AA$1,"-",AI59) -> -58 | AK59: =IFERROR(VLOOKUP(AJ59,$AD$2:$AG$1120,3,0),"") | AL59: =IFERROR(VLOOKUP(AJ59,$AD$2:$AG$1120,4,0),"") | AN59: BANCO UNIÓN | AO59: BANCO UNIÓN | AQ59: 303 | AS59: 1052 | AT59: 101 | AU59: Elaboración de almidones y productos derivados del almidón | AV59: 4.14 | AX59: 1011 | AY59: Procesamiento y conservación de carne y productos cárnicos. | BA59: Comercio al por menor de productos farmaceuticos y medicinales, cosmeticos y articulos de tocador en establecimientos especializados, incluye comercio de productos farmaceuticos, medicinales, botanicos, homeopaticos, ortopedicos, ortesicos y protesicos, cosmeticos, farmaceuticos veterinarios, tiendas naturistas | BB59: 1477301
K60: Dirección de Cobertura | L60: 4100 | T60: CUBA | U60: 199 | AB60: Antioquia | AC60: 05 | AD60: =CONCATENATE(AC60,"-",AE60) -> 05-59 | AE60: =IF(AB60=AB59,1+AE59,1) -> 59 | AF60: ITAGUI | AG60: 360 | AI60: 59 | AJ60: =CONCATENATE($AA$1,"-",AI60) -> -59 | AK60: =IFERROR(VLOOKUP(AJ60,$AD$2:$AG$1120,3,0),"") | AL60: =IFERROR(VLOOKUP(AJ60,$AD$2:$AG$1120,4,0),"") | AN60: DUMMY SSF | AO60: DUMMY SSF | AQ60: 700 | AS60: 1061 | AT60: 304 | AU60: Trilla de café | AV60: 9.66 | AX60: 1012 | AY60: Procesamiento y conservación de pescados, crustáceos y moluscos. | BA60: Comercio al por menor de otros productos nuevos en establecimientos especializados, incluye comercio de equipo y articulos fotograficos, cinematograficos, opticos y de precision, relojes, joyas y articulos de plata en general, armas, municiones, sellos y productos no alimenticios, floristerias, actividades de galerias de arte comerciales | BB60: 1477401
C61: SIGNIFICADO | D61: mensaje de validación | K61: Dirección de Bienestar Estudiantil | L61: 4200 | T61: CURACAO | U61: 789 | AB61: Antioquia | AC61: 05 | AD61: =CONCATENATE(AC61,"-",AE61) -> 05-60 | AE61: =IF(AB61=AB60,1+AE60,1) -> 60 | AF61: ITUANGO | AG61: 361 | AI61: 60 | AJ61: =CONCATENATE($AA$1,"-",AI61) -> -60 | AK61: =IFERROR(VLOOKUP(AJ61,$AD$2:$AG$1120,3,0),"") | AL61: =IFERROR(VLOOKUP(AJ61,$AD$2:$AG$1120,4,0),"") | AN61: BAN100 S. A. | AO61: BAN100 S. A. | AQ61: 558 | AS61: 1062 | AT61: 101 | AU61: Descafeinado, tostión y molienda del café | AV61: 4.14 | AX61: 1020 | AY61: Procesamiento y conservación de frutas, legumbres, hortalizas y tubérculos. | BA61: Comercio al por menor de otros productos nuevos en establecimientos especializados, incluye comercio de articulos opticos y de precision, relojes, joyas y las actividades de opticas | BB61: 1477402
C62: CONTATENACIÓN FALTA DILIGENCIAR | D62: =_xlfn.CONCAT(D3:D56) -> - Número de Identificación Tributaria (NIT) - DV - Tipo de Documento - Número de Identificación - Verificar el Número de Identificación - Primer Apellido - Primer Nombre - Indicar SI es o NO pensionado - Indique la Dirección tal y como aparece en el RUT - País - Departamento - Municipio - Teléfono 1 - Teléfono 2 - Banco - Sucursal - Tipo Cuenta - No Cuenta Bancaria - Actividad Económica RUT - Actividad económica RUT NO existe - por favor verificar - Actividad Económica RIT - Actividad economica RIT NO existe - por favor verificar - Régimen - No Contrato - Año Contrato - Valor Total del Contrato - Valor Pago Mensual según Contrato - Fecha Acta de Inicio - Fecha terminación Contrato - VIGENCIA FUTURA - Cesión - Área Funcional de la SED - Nombre Interventor Contrato - Cargo Interventor Contrato - Nombre Operativo - Identificación Operativo - Codigo ARL - Pregunta C1 - Pregunta C2 - Pregunta C3 - Pregunta C4 - Entidad (AFC) - NIT (AFC) - Valor Mensual (AFC) - Entidad (Pensiones Voluntarias) - NIT (Pensiones Voluntarias) - Valor Mensual (Pensiones Voluntarias) - Número CRP - Fecha del CRP | K62: Dirección de Construcción y Conservación de Establecimientos Educativos | L62: 4300 | T62: DINAMARCA | U62: 232 | AB62: Antioquia | AC62: 05 | AD62: =CONCATENATE(AC62,"-",AE62) -> 05-61 | AE62: =IF(AB62=AB61,1+AE61,1) -> 61 | AF62: JARDÍN | AG62: 364 | AI62: 61 | AJ62: =CONCATENATE($AA$1,"-",AI62) -> -61 | AK62: =IFERROR(VLOOKUP(AJ62,$AD$2:$AG$1120,3,0),"") | AL62: =IFERROR(VLOOKUP(AJ62,$AD$2:$AG$1120,4,0),"") | AN62: BANCOLOMBIA PUERTO RICO | AO62: BANCOLOMBIA PUERTO RICO | AQ62: 984 | AS62: 1063 | AT62: 101 | AU62: Elaboración de otros derivados del café | AV62: 4.14 | AX62: 1030 | AY62: Elaboración de aceites y grasas de origen vegetal y animal. | BA62: Comercio al por menor de articulos de segunda mano, incluye comercio de libros, antigüedades, prendas de vestir y otros articulos de segunda mano, comercializacion de articulos mediante contrato de compraventa con pacto de retroventa, casas de subastas (al por menor) | BB62: 1477501
C63: VALIDADOR IVA | D63: =AND('FORMATO ACTUALIZACIÓN DATOS'!AU39="NO RESPONSABLE IVA",'FORMATO ACTUALIZACIÓN DATOS'!AW53>0) -> FALSE | K63: Dirección de Dotaciones Escolares | L63: 4400 | T63: DJIBOUTI | U63: 783 | AB63: Antioquia | AC63: 05 | AD63: =CONCATENATE(AC63,"-",AE63) -> 05-62 | AE63: =IF(AB63=AB62,1+AE62,1) -> 62 | AF63: JERICÓ | AG63: 368 | AI63: 62 | AJ63: =CONCATENATE($AA$1,"-",AI63) -> -62 | AK63: =IFERROR(VLOOKUP(AJ63,$AD$2:$AG$1120,3,0),"") | AL63: =IFERROR(VLOOKUP(AJ63,$AD$2:$AG$1120,4,0),"") | AN63: Iris CF Compañía de Financiamiento S. A. | AO63: Iris CF Compañía de Financiamiento S. A. | AQ63: 637 | AS63: 1071 | AT63: 101 | AU63: Elaboración y refinación de azúcar | AV63: 4.14 | AX63: 1040 | AY63: Elaboración de productos lácteos. | BA63: Comercio al por menor de alimentos, bebidas y tabaco en puestos de venta moviles, incluye venta de alimentos, bebidas y tabaco en puestos de venta y mercados. | BB63: 1478101
C64: FECHA ACTUAL | D64: =TODAY() -> 46204 | K64: Subsecretaría De Gestión Institucional | L64: 5000 | T64: DOMINICA | U64: 235 | AB64: Antioquia | AC64: 05 | AD64: =CONCATENATE(AC64,"-",AE64) -> 05-63 | AE64: =IF(AB64=AB63,1+AE63,1) -> 63 | AF64: LA CEJA | AG64: 376 | AI64: 63 | AJ64: =CONCATENATE($AA$1,"-",AI64) -> -63 | AK64: =IFERROR(VLOOKUP(AJ64,$AD$2:$AG$1120,3,0),"") | AL64: =IFERROR(VLOOKUP(AJ64,$AD$2:$AG$1120,4,0),"") | AN64: PIBANK | AO64: PIBANK | AQ64: 560 | AS64: 1072 | AT64: 101 | AU64: Elaboración de panela | AV64: 4.14 | AX64: 1051 | AY64: Elaboración de productos de molinería. | BA64: Comercio al por menor de productos textiles, prendas de vestir y calzado en puestos de venta moviles, incluye comercio al por menor de productos textiles, prendas de vestir y calzado en puestos de venta y mercados. | BB64: 1478201
C65: MENSAJE FORMULARIO INCOMPLETO | D65: =CONCATENATE("Por favor verifique la información de :",D62) -> Por favor verifique la información de : - Número de Identificación Tributaria (NIT) - DV - Tipo de Documento - Número de Identificación - Verificar el Número de Identificación - Primer Apellido - Primer Nombre - Indicar SI es o NO pensionado - Indique la Dirección tal y como aparece en el RUT - País - Departamento - Municipio - Teléfono 1 - Teléfono 2 - Banco - Sucursal - Tipo Cuenta - No Cuenta Bancaria - Actividad Económica RUT - Actividad económica RUT NO existe - por favor verificar - Actividad Económica RIT - Actividad economica RIT NO existe - por favor verificar - Régimen - No Contrato - Año Contrato - Valor Total del Contrato - Valor Pago Mensual según Contrato - Fecha Acta de Inicio - Fecha terminación Contrato - VIGENCIA FUTURA - Cesión - Área Funcional de la SED - Nombre Interventor Contrato - Cargo Interventor Contrato - Nombre Operativo - Identificación Operativo - Codigo ARL - Pregunta C1 - Pregunta C2 - Pregunta C3 - Pregunta C4 - Entidad (AFC) - NIT (AFC) - Valor Mensual (AFC) - Entidad (Pensiones Voluntarias) - NIT (Pensiones Voluntarias) - Valor Mensual (Pensiones Voluntarias) - Número CRP - Fecha del CRP | K65: Dirección de Talento Humano | L65: 5100 | T65: ECUADOR | U65: 239 | AB65: Antioquia | AC65: 05 | AD65: =CONCATENATE(AC65,"-",AE65) -> 05-64 | AE65: =IF(AB65=AB64,1+AE64,1) -> 64 | AF65: LA ESTRELLA | AG65: 380 | AI65: 64 | AJ65: =CONCATENATE($AA$1,"-",AI65) -> -64 | AK65: =IFERROR(VLOOKUP(AJ65,$AD$2:$AG$1120,3,0),"") | AL65: =IFERROR(VLOOKUP(AJ65,$AD$2:$AG$1120,4,0),"") | AN65: BANQUE DE FRANCE | AO65: BANQUE DE FRANCE | AQ65: 986 | AS65: 1081 | AT65: 101 | AU65: Elaboración de productos de panadería | AV65: 4.14 | AX65: 1052 | AY65: Elaboración de almidones y productos derivados del almidón. | BA65: Comercio al por menor de otros productos en puestos de venta moviles, incluye comercio al por menor de otros productos en puestos de venta y mercados como por ejemplo: tapices y alfombras, libros, juguetes, aparatos de uso domestico; productos electronicos de consumo, grabaciones de musica y video, etcetera | BB65: 1478901
C66: MENSAJE FORMULARIO COMPLETO | D66: ="Información completa, en constancia se suscribe el presente formulario el dia "&TEXT(D64,"dd/mm/yyyy") -> Información completa, en constancia se suscribe el presente formulario el dia 01/07/yyyy | K66: Oficina de Personal | L66: 5110 | T66: EGIPTO | U66: 240 | AB66: Antioquia | AC66: 05 | AD66: =CONCATENATE(AC66,"-",AE66) -> 05-65 | AE66: =IF(AB66=AB65,1+AE65,1) -> 65 | AF66: LA PINTADA | AG66: 390 | AI66: 65 | AJ66: =CONCATENATE($AA$1,"-",AI66) -> -65 | AK66: =IFERROR(VLOOKUP(AJ66,$AD$2:$AG$1120,3,0),"") | AL66: =IFERROR(VLOOKUP(AJ66,$AD$2:$AG$1120,4,0),"") | AN66: BBVA | AO66: BBVA | AQ66: 987 | AS66: 1082 | AT66: 101 | AU66: Elaboración de cacao, chocolate y productos de confitería | AV66: 4.14 | AX66: 1061 | AY66: Trilla de café. | BA66: Comercio al por menor realizado a traves de internet, incluye la venta directa y subastas a traves de internet. | BB66: 1479101
C67: MENSAJE FORMULARIO SIN DILIGENCIAR | D67: Formulario sin diligenciar | K67: Grupo De Certificaciones Laborales | L67: 5111 | T67: EL SALVADOR | U67: 242 | AB67: Antioquia | AC67: 05 | AD67: =CONCATENATE(AC67,"-",AE67) -> 05-66 | AE67: =IF(AB67=AB66,1+AE66,1) -> 66 | AF67: LA UNIÓN | AG67: 400 | AI67: 66 | AJ67: =CONCATENATE($AA$1,"-",AI67) -> -66 | AK67: =IFERROR(VLOOKUP(AJ67,$AD$2:$AG$1120,3,0),"") | AL67: =IFERROR(VLOOKUP(AJ67,$AD$2:$AG$1120,4,0),"") | AN67: NU BANK | AO67: NU BANK | AQ67: 809 | AS67: 1083 | AT67: 101 | AU67: Elaboración de macarrones, fideos, alcuzcuz y productos farináceos similares | AV67: 4.14 | AX67: 1062 | AY67: Descafeinado, tostión y molienda del café. | BA67: Comercio al por menor realizado a traves de casas de venta o por correo, incluye ventas directas a traves de television, radio y telefono por anuncios, catalogos o cualquier otro medio de publicidad. | BB67: 1479201
C68: MENSAJE FORMULARIO | D68: =IF(B57=54,D66,IF(B57=4,D67,D65)) -> Por favor verifique la información de : - Número de Identificación Tributaria (NIT) - DV - Tipo de Documento - Número de Identificación - Verificar el Número de Identificación - Primer Apellido - Primer Nombre - Indicar SI es o NO pensionado - Indique la Dirección tal y como aparece en el RUT - País - Departamento - Municipio - Teléfono 1 - Teléfono 2 - Banco - Sucursal - Tipo Cuenta - No Cuenta Bancaria - Actividad Económica RUT - Actividad económica RUT NO existe - por favor verificar - Actividad Económica RIT - Actividad economica RIT NO existe - por favor verificar - Régimen - No Contrato - Año Contrato - Valor Total del Contrato - Valor Pago Mensual según Contrato - Fecha Acta de Inicio - Fecha terminación Contrato - VIGENCIA FUTURA - Cesión - Área Funcional de la SED - Nombre Interventor Contrato - Cargo Interventor Contrato - Nombre Operativo - Identificación Operativo - Codigo ARL - Pregunta C1 - Pregunta C2 - Pregunta C3 - Pregunta C4 - Entidad (AFC) - NIT (AFC) - Valor Mensual (AFC) - Entidad (Pensiones Voluntarias) - NIT (Pensiones Voluntarias) - Valor Mensual (Pensiones Voluntarias) - Número CRP - Fecha del CRP | K68: Oficina de Escalafón Docente | L68: 5120 | T68: EMIRATOS ARABES UNID | U68: 244 | AB68: Antioquia | AC68: 05 | AD68: =CONCATENATE(AC68,"-",AE68) -> 05-67 | AE68: =IF(AB68=AB67,1+AE67,1) -> 67 | AF68: LIBORINA | AG68: 411 | AI68: 67 | AJ68: =CONCATENATE($AA$1,"-",AI68) -> -67 | AK68: =IFERROR(VLOOKUP(AJ68,$AD$2:$AG$1120,3,0),"") | AL68: =IFERROR(VLOOKUP(AJ68,$AD$2:$AG$1120,4,0),"") | AN68: RappiPay Compañía de Financiamiento S.A. | AO68: RappiPay Compañía de Financiamiento S.A. | AQ68: 811 | AS68: 1084 | AT68: 101 | AU68: Elaboración de comidas y platos preparados | AV68: 4.14 | AX68: 1063 | AY68: Otros derivados del café. | BA68: Otros tipos de comercio al por menor no realizado en establecimientos, puestos de venta o mercados, incluye comercio al por menor de productos de todo tipo como las ventas directas y ventas realizadas por vendedores a domicilio, venta mediante maquinas expendedoras y a cambio de una retribucion o por contrata, agentes comisionistas (no en almacenes) , actividades de subastas diferentes de las realizadas por internet; venta directa de combustible (combustible para calefaccion, leña) entregado directamente en los establecimientos de los clientes | BB68: 1479901
C69: juramentación | D69: en calidad de contratista manifiesto bajo la gravedad del juramento que la información es veridica y entiendo que soy responsable por los errores u omisiones que genere a la Entidad Contable Pública -Bogotá D.C. por la inexactitud de la misma, y autorizo a la entidad para actualizar la información en las bases de datos, en especial las de la SED, la SHD, la CGN, DIAN y demás entidades de aseguramiento y control del estado. Al firmar este documento, autorizo de manera previa, expresa e informada a la Secretaría de Educación del Distrito para que realice el tratamiento de mis datos personales aquí suministrados. Esta información será utilizada con fines de actualización de información del tercero, conforme a la Ley 1581 de 2012 y a la Política de Tratamiento de Datos disponible en www.educacionbogota.gov.co. Como titular, tengo derecho a conocer, actualizar, rectificar y solicitar la supresión de mis datos, así como a presentar quejas ante la Superintendencia de Industria y Comercio Con la firma del presente formato doy constancia que conozco las condiciones tributarias y obligaciones del mismo derivado del presente contrato. | K69: Oficina de Nómina | L69: 5130 | T69: ERITREA | U69: 243 | AB69: Antioquia | AC69: 05 | AD69: =CONCATENATE(AC69,"-",AE69) -> 05-68 | AE69: =IF(AB69=AB68,1+AE68,1) -> 68 | AF69: MACEO | AG69: 425 | AI69: 68 | AJ69: =CONCATENATE($AA$1,"-",AI69) -> -68 | AK69: =IFERROR(VLOOKUP(AJ69,$AD$2:$AG$1120,3,0),"") | AL69: =IFERROR(VLOOKUP(AJ69,$AD$2:$AG$1120,4,0),"") | AN69: JFK COOPERATIVA FINANCIERA | AO69: JFK COOPERATIVA FINANCIERA | AQ69: 286 | AS69: 1089 | AT69: 101 | AU69: Elaboración de otros productos alimenticios n.c.p. | AV69: 4.14 | AX69: 1071 | AY69: Elaboración y refinación de azúcar. | BA69: EMPRESAS DEDICADAS AL COMERCIO, MANTENIMIENTO Y REPARACIÓN DE MOTOCICLETAS Y DE SUS PARTES, PIEZAS Y ACCESORIOS INCLUYE LA COMERCIALIZACIÓN DE MOTOCICLETAS Y TRINEOS MOTORIZADOS NUEVOS Y USADOS, PARTES PIEZAS Y ACCESORIOS LAS ACTIVIDADES DE MANTENIMIENTO Y REPARACIÓN | BB69: 1504001
K70: Dirección de Contratación | L70: 5200 | T70: ESLOVAQUIA | U70: 246 | AB70: Antioquia | AC70: 05 | AD70: =CONCATENATE(AC70,"-",AE70) -> 05-69 | AE70: =IF(AB70=AB69,1+AE69,1) -> 69 | AF70: MARINILLA | AG70: 440 | AI70: 69 | AJ70: =CONCATENATE($AA$1,"-",AI70) -> -69 | AK70: =IFERROR(VLOOKUP(AJ70,$AD$2:$AG$1120,3,0),"") | AL70: =IFERROR(VLOOKUP(AJ70,$AD$2:$AG$1120,4,0),"") | AN70: LULO BANK | AO70: LULO BANK | AQ70: 70 | AS70: 1090 | AT70: 101 | AU70: Elaboración de alimentos preparados para animales | AV70: 4.14 | AX70: 1072 | AY70: Elaboración de panela. | BA70: EMPRESAS DEDICADAS AL COMERCIO AL POR MENOR DE LUBRICANTES (ACEITES, GRASAS), ADITIVOS Y PRODUCTOS DE LIMPIEZA PARA VEHÍCULOS AUTOMOTORES | BB70: 1505201
K71: Oficina de Apoyo Precontractual | L71: 5210 | T71: ESLOVENIA | U71: 247 | AB71: Antioquia | AC71: 05 | AD71: =CONCATENATE(AC71,"-",AE71) -> 05-70 | AE71: =IF(AB71=AB70,1+AE70,1) -> 70 | AF71: MONTEBELLO | AG71: 467 | AI71: 70 | AJ71: =CONCATENATE($AA$1,"-",AI71) -> -70 | AK71: =IFERROR(VLOOKUP(AJ71,$AD$2:$AG$1120,3,0),"") | AL71: =IFERROR(VLOOKUP(AJ71,$AD$2:$AG$1120,4,0),"") | AN71: BTG PACTUAL | AO71: BTG PACTUAL | AQ71: 805 | AS71: 1101 | AT71: 103 | AU71: Destilación, rectificación y mezcla de bebidas alcohólicas | AV71: 11.04 | AX71: 1081 | AY71: Elaboración de productos de panadería. | BA71: EMPRESAS DEDICADAS AL COMERCIO AL POR MAYOR A CAMBIO DE UNA RETRIBUCIÓN O POR CONTRATA DE PRODUCTOS AGRÍCOLAS (EXCEPTO CAFÉ), SILVÍCOLA Y DE ANIMALES VIVOS Y SUS PRODUCTOS INCLUYE LA VENTA DE AVES DE CORRAL Y/O IMPLEMENTOS PARA AVICULTURA, DE AVES MUERTAS Y/O MENUDENCIAS | BB71: 1511101
K72: Oficina de Contratos | L72: 5220 | T72: ESPAÑA | U72: 245 | AB72: Antioquia | AC72: 05 | AD72: =CONCATENATE(AC72,"-",AE72) -> 05-71 | AE72: =IF(AB72=AB71,1+AE71,1) -> 71 | AF72: MURINDÓ | AG72: 475 | AI72: 71 | AJ72: =CONCATENATE($AA$1,"-",AI72) -> -71 | AK72: =IFERROR(VLOOKUP(AJ72,$AD$2:$AG$1120,3,0),"") | AL72: =IFERROR(VLOOKUP(AJ72,$AD$2:$AG$1120,4,0),"") | AN72: J. P. MORGAN | AO72: J. P. MORGAN | AQ72: 71 | AS72: 1102 | AT72: 103 | AU72: Elaboración de bebidas fermentadas no destiladas | AV72: 11.04 | AX72: 1082 | AY72: Elaboración de cacao, chocolate y productos de confitería. | BA72: EMPRESAS DEDICADAS AL COMERCIO AL POR MAYOR A CAMBIO DE UNA RETRIBUCIÓN O POR CONTRATA DE CAFÉ PERGAMINO | BB72: 1511201
K73: Dirección de Servicios Administrativos | L73: 5300 | T73: ESTADOS UNIDOS | U73: 249 | AB73: Antioquia | AC73: 05 | AD73: =CONCATENATE(AC73,"-",AE73) -> 05-72 | AE73: =IF(AB73=AB72,1+AE72,1) -> 72 | AF73: MUTATÁ | AG73: 480 | AI73: 72 | AJ73: =CONCATENATE($AA$1,"-",AI73) -> -72 | AK73: =IFERROR(VLOOKUP(AJ73,$AD$2:$AG$1120,3,0),"") | AL73: =IFERROR(VLOOKUP(AJ73,$AD$2:$AG$1120,4,0),"") | AN73: BANQUE ET CAISSE D'EPARGNE DE L'ÉTAT | AO73: BANQUE ET CAISSE D'EPARGNE DE L'ÉTAT | AQ73: 983 | AS73: 1103 | AT73: 103 | AU73: Producción de malta, elaboración de cervezas y otras bebidas malteadas | AV73: 11.04 | AX73: 1083 | AY73: Elaboración de macarrones, fideos, alcuzcuz y productos farináceos similares. | BA73: EMPRESAS DEDICADAS AL COMERCIO AL POR MAYOR A CAMBIO DE UNA RETRIBUCIÓN O POR CONTRATA DE PRODUCTOS NCP | BB73: 1511901
K74: Archivo SED | L74: 4121 | T74: ESTONIA | U74: 251 | AB74: Antioquia | AC74: 05 | AD74: =CONCATENATE(AC74,"-",AE74) -> 05-73 | AE74: =IF(AB74=AB73,1+AE73,1) -> 73 | AF74: NARIÑO | AG74: 483 | AI74: 73 | AJ74: =CONCATENATE($AA$1,"-",AI74) -> -73 | AK74: =IFERROR(VLOOKUP(AJ74,$AD$2:$AG$1120,3,0),"") | AL74: =IFERROR(VLOOKUP(AJ74,$AD$2:$AG$1120,4,0),"") | AN74: UMB BANK | AO74: UMB BANK | AQ74: 983 | AS74: 1104 | AT74: 103 | AU74: Elaboración de bebidas no alcohólicas, producción de aguas minerales y de otras aguas embotelladas | AV74: 11.04 | AX74: 1084 | AY74: Elaboración de comidas y platos preparados. | BA74: EMPRESAS DEDICADAS AL COMERCIO AL POR MAYOR DE CAFÉ PERGAMINO | BB74: 1512201
K75: Oficina de Servicio al Ciudadano | L75: 5310 | T75: ETIOPIA | U75: 253 | AB75: Antioquia | AC75: 05 | AD75: =CONCATENATE(AC75,"-",AE75) -> 05-74 | AE75: =IF(AB75=AB74,1+AE74,1) -> 74 | AF75: NECOCLÍ | AG75: 490 | AI75: 74 | AJ75: =CONCATENATE($AA$1,"-",AI75) -> -74 | AK75: =IFERROR(VLOOKUP(AJ75,$AD$2:$AG$1120,3,0),"") | AL75: =IFERROR(VLOOKUP(AJ75,$AD$2:$AG$1120,4,0),"") | AN75: WELLS FARGO | AO75: WELLS FARGO | AQ75: 982 | AS75: 1200 | AT75: 103 | AU75: Elaboración de productos de tabaco | AV75: 11.04 | AX75: 1089 | AY75: Elaboración de otros productos alimenticios n.c.p. | BA75: EMPRESAS DEDICADAS AL COMERCIO AL POR MAYOR DE FLORES Y PLANTAS ORNAMENTALES | BB75: 1512301
K76: Dirección Financiera | L76: 5400 | T76: FEROE, ISLAS | U76: 259 | AB76: Antioquia | AC76: 05 | AD76: =CONCATENATE(AC76,"-",AE76) -> 05-75 | AE76: =IF(AB76=AB75,1+AE75,1) -> 75 | AF76: NECHÍ | AG76: 495 | AI76: 75 | AJ76: =CONCATENATE($AA$1,"-",AI76) -> -75 | AK76: =IFERROR(VLOOKUP(AJ76,$AD$2:$AG$1120,3,0),"") | AL76: =IFERROR(VLOOKUP(AJ76,$AD$2:$AG$1120,4,0),"") | AN76: U.S. Bank National Association | AO76: U.S. Bank National Association | AQ76: 981 | AS76: 1311 | AT76: 103 | AU76: Preparación e hilatura de fibras textiles | AV76: 11.04 | AX76: 1090 | AY76: Elaboración de alimentos preparados para animales. | BA76: EMPRESAS DEDICADAS AL COMERCIO AL POR MAYOR DE MATERIAS PRIMAS PECUARIAS, ANIMALES VIVOS Y SUS PRODUCTOS | BB76: 1512401
K77: Oficina de Presupuesto | L77: 5410 | T77: FIJI | U77: 870 | AB77: Antioquia | AC77: 05 | AD77: =CONCATENATE(AC77,"-",AE77) -> 05-76 | AE77: =IF(AB77=AB76,1+AE76,1) -> 76 | AF77: OLAYA | AG77: 501 | AI77: 76 | AJ77: =CONCATENATE($AA$1,"-",AI77) -> -76 | AK77: =IFERROR(VLOOKUP(AJ77,$AD$2:$AG$1120,3,0),"") | AL77: =IFERROR(VLOOKUP(AJ77,$AD$2:$AG$1120,4,0),"") | AN77: BNP PARIBAS | AO77: BNP PARIBAS | AQ77: 980 | AS77: 1312 | AT77: 103 | AU77: Tejeduría de productos textiles | AV77: 11.04 | AX77: 1101 | AY77: Destilación, rectificación y mezcla de bebidas alcohólicas. | BA77: EMPRESAS DEDICADAS AL COMERCIO AL POR MAYOR DE PRODUCTOS ALIMENTICIOS, EXCEPTO CAFÉ TRILLADO | BB77: 1512501
K78: Oficina de Tesorería y Contabilidad | L78: 5420 | T78: FILIPINAS | U78: 267 | AB78: Antioquia | AC78: 05 | AD78: =CONCATENATE(AC78,"-",AE78) -> 05-77 | AE78: =IF(AB78=AB77,1+AE77,1) -> 77 | AF78: PEÑOL | AG78: 541 | AI78: 77 | AJ78: =CONCATENATE($AA$1,"-",AI78) -> -77 | AK78: =IFERROR(VLOOKUP(AJ78,$AD$2:$AG$1120,3,0),"") | AL78: =IFERROR(VLOOKUP(AJ78,$AD$2:$AG$1120,4,0),"") | AS78: 1313 | AT78: 103 | AU78: Acabado de productos textiles | AV78: 11.04 | AX78: 1102 | AY78: Elaboración de bebidas fermentadas no destiladas. | BA78: EMPRESAS DEDICADAS AL COMERCIO AL POR MAYOR DE CAFÉ TRILLADO | BB78: 1512601
T79: FINLANDIA | U79: 271 | AB79: Antioquia | AC79: 05 | AD79: =CONCATENATE(AC79,"-",AE79) -> 05-78 | AE79: =IF(AB79=AB78,1+AE78,1) -> 78 | AF79: PEQUE | AG79: 543 | AI79: 78 | AJ79: =CONCATENATE($AA$1,"-",AI79) -> -78 | AK79: =IFERROR(VLOOKUP(AJ79,$AD$2:$AG$1120,3,0),"") | AL79: =IFERROR(VLOOKUP(AJ79,$AD$2:$AG$1120,4,0),"") | AN79: Tipo Cuenta | AO79: COD | AS79: 1391 | AT79: 103 | AU79: Fabricación de tejidos de punto y ganchillo | AV79: 11.04 | AX79: 1103 | AY79: Producción de malta, elaboración de cervezas y otras bebidas malteadas. | BA79: EMPRESAS DEDICADAS AL COMERCIO AL POR MAYOR DE PRODUCTOS TEXTILES Y PRODUCTOS CONFECCIONADOS PARA USO DOMESTICO. | BB79: 1513101
T80: FRANCIA | U80: 275 | AB80: Antioquia | AC80: 05 | AD80: =CONCATENATE(AC80,"-",AE80) -> 05-79 | AE80: =IF(AB80=AB79,1+AE79,1) -> 79 | AF80: PUEBLORRICO | AG80: 576 | AI80: 79 | AJ80: =CONCATENATE($AA$1,"-",AI80) -> -79 | AK80: =IFERROR(VLOOKUP(AJ80,$AD$2:$AG$1120,3,0),"") | AL80: =IFERROR(VLOOKUP(AJ80,$AD$2:$AG$1120,4,0),"") | AN80: Corriente | AO80: 1 | AS80: 1392 | AT80: 103 | AU80: Confección de artículos con materiales textiles, excepto prendas de vestir | AV80: 11.04 | AX80: 1104 | AY80: Elaboración de bebidas no alcohólicas, producción de aguas minerales y de otras aguas embotelladas. | BA80: EMPRESAS DEDICADAS AL COMERCIO AL POR MAYOR DE PRENDAS DE VESTIR, ACCESORIOS DE PRENDAS DE VESTIR Y ARTÍCULOS ELABORADOS EN PIEL. | BB80: 1513201
T81: GABON | U81: 281 | AB81: Antioquia | AC81: 05 | AD81: =CONCATENATE(AC81,"-",AE81) -> 05-80 | AE81: =IF(AB81=AB80,1+AE80,1) -> 80 | AF81: PUERTO BERRÍO | AG81: 579 | AI81: 80 | AJ81: =CONCATENATE($AA$1,"-",AI81) -> -80 | AK81: =IFERROR(VLOOKUP(AJ81,$AD$2:$AG$1120,3,0),"") | AL81: =IFERROR(VLOOKUP(AJ81,$AD$2:$AG$1120,4,0),"") | AN81: Ahorros | AO81: 2 | AS81: 1393 | AT81: 103 | AU81: Fabricación de tapetes y alfombras para pisos | AV81: 11.04 | AX81: 1200 | AY81: Elaboración de productos de tabaco. | BA81: EMPRESAS DEDICADAS AL COMERCIO AL POR MAYOR DE CALZADO | BB81: 1513301
T82: GAMBIA | U82: 285 | AB82: Antioquia | AC82: 05 | AD82: =CONCATENATE(AC82,"-",AE82) -> 05-81 | AE82: =IF(AB82=AB81,1+AE81,1) -> 81 | AF82: PUERTO NARE | AG82: 585 | AI82: 81 | AJ82: =CONCATENATE($AA$1,"-",AI82) -> -81 | AK82: =IFERROR(VLOOKUP(AJ82,$AD$2:$AG$1120,3,0),"") | AL82: =IFERROR(VLOOKUP(AJ82,$AD$2:$AG$1120,4,0),"") | AN82: Daviplata | AO82: 3 | AS82: 1394 | AT82: 103 | AU82: Fabricación de cuerdas, cordeles, cables, bramantes y redes | AV82: 11.04 | AX82: 1311 | AY82: Preparación e hilatura de fibras textiles. | BA82: EMPRESAS DEDICADAS AL COMERCIO AL POR MAYOR DE APARATOS, ARTÍCULOS Y EQUIPO DE USO DOMESTICO | BB82: 1513401
T83: GAZA Y JERICO | U83: 286 | AB83: Antioquia | AC83: 05 | AD83: =CONCATENATE(AC83,"-",AE83) -> 05-82 | AE83: =IF(AB83=AB82,1+AE82,1) -> 82 | AF83: PUERTO TRIUNFO | AG83: 591 | AI83: 82 | AJ83: =CONCATENATE($AA$1,"-",AI83) -> -82 | AK83: =IFERROR(VLOOKUP(AJ83,$AD$2:$AG$1120,3,0),"") | AL83: =IFERROR(VLOOKUP(AJ83,$AD$2:$AG$1120,4,0),"") | AS83: 1399 | AT83: 103 | AU83: Fabricación de otros artículos textiles n.c.p. | AV83: 11.04 | AX83: 1312 | AY83: Tejeduría de productos textiles. | BA83: EMPRESAS DEDICADAS AL COMERCIO AL POR MAYOR DE PRODUCTOS FARMACÉUTICOS, MEDICINALES, COSMÉTICOS Y DE TOCADOR | BB83: 1513501
T84: GEORGIA | U84: 287 | AB84: Antioquia | AC84: 05 | AD84: =CONCATENATE(AC84,"-",AE84) -> 05-83 | AE84: =IF(AB84=AB83,1+AE83,1) -> 83 | AF84: REMEDIOS | AG84: 604 | AI84: 83 | AJ84: =CONCATENATE($AA$1,"-",AI84) -> -83 | AK84: =IFERROR(VLOOKUP(AJ84,$AD$2:$AG$1120,3,0),"") | AL84: =IFERROR(VLOOKUP(AJ84,$AD$2:$AG$1120,4,0),"") | AS84: 1410 | AT84: 101 | AU84: Confección de prendas de vestir, excepto prendas de piel | AV84: 4.14 | AX84: 1313 | AY84: Acabado de productos textiles. | BA84: EMPRESAS DEDICADAS AL COMERCIO AL POR MAYOR DE EQUIPOS MÉDICOS Y QUIRÚRGICOS Y DE APARATOS ORTESICOS Y PROTÉSICOS | BB84: 1513601
T85: GHANA | U85: 289 | AB85: Antioquia | AC85: 05 | AD85: =CONCATENATE(AC85,"-",AE85) -> 05-84 | AE85: =IF(AB85=AB84,1+AE84,1) -> 84 | AF85: RETIRO | AG85: 607 | AI85: 84 | AJ85: =CONCATENATE($AA$1,"-",AI85) -> -84 | AK85: =IFERROR(VLOOKUP(AJ85,$AD$2:$AG$1120,3,0),"") | AL85: =IFERROR(VLOOKUP(AJ85,$AD$2:$AG$1120,4,0),"") | AS85: 1511 | AT85: 103 | AU85: Curtido y recurtido de cueros; recurtido y teñido de pieles. | AV85: 11.04 | AX85: 1391 | AY85: Fabricación de tejidos de punto y ganchillo. | BA85: EMPRESAS DEDICADAS AL COMERCIO AL POR MAYOR DE PINTURAS Y PRODUCTOS CONEXOS | BB85: 1514201
T86: GIBRALTAR | U86: 293 | AB86: Antioquia | AC86: 05 | AD86: =CONCATENATE(AC86,"-",AE86) -> 05-85 | AE86: =IF(AB86=AB85,1+AE85,1) -> 85 | AF86: RIONEGRO | AG86: 615 | AI86: 85 | AJ86: =CONCATENATE($AA$1,"-",AI86) -> -85 | AK86: =IFERROR(VLOOKUP(AJ86,$AD$2:$AG$1120,3,0),"") | AL86: =IFERROR(VLOOKUP(AJ86,$AD$2:$AG$1120,4,0),"") | AS86: 1512 | AT86: 103 | AU86: Fabricación de artículos de viaje, bolsos de mano y artículos similares elaborados en cuero, y fabricación de artículos de talabartería y guarnicionería. | AV86: 11.04 | AX86: 1392 | AY86: Confección de artículos con materiales textiles, excepto prendas de vestir. | BA86: EMPRESAS DEDICADAS AL COMERCIO AL POR MAYOR DE COMBUSTIBLES SÓLIDOS, LÍQUIDOS, GASEOSOS Y PRODUCTOS CONEXOS" | BB86: 1515101
T87: GRANADA | U87: 297 | AB87: Antioquia | AC87: 05 | AD87: =CONCATENATE(AC87,"-",AE87) -> 05-86 | AE87: =IF(AB87=AB86,1+AE86,1) -> 86 | AF87: SABANALARGA | AG87: 628 | AI87: 86 | AJ87: =CONCATENATE($AA$1,"-",AI87) -> -86 | AK87: =IFERROR(VLOOKUP(AJ87,$AD$2:$AG$1120,3,0),"") | AL87: =IFERROR(VLOOKUP(AJ87,$AD$2:$AG$1120,4,0),"") | AS87: 1513 | AT87: 103 | AU87: Fabricación de artículos de viaje, bolsos de mano y artículos similares; artículos de talabartería y guarnicionería elaborados en otros materiales | AV87: 11.04 | AX87: 1393 | AY87: Fabricación de tapetes y alfombras para pisos. | BA87: EMPRESAS DEDICADAS AL COMERCIO AL POR MAYOR DE PRODUCTOS QUÍMICOS BÁSICOS, PLÁSTICOS Y CAUCHO EN FORMAS PRIMARIAS Y PRODUCTOS QUÍMICOS DE USO AGROPECUARIO | BB87: 1515301
T88: GRECIA | U88: 301 | AB88: Antioquia | AC88: 05 | AD88: =CONCATENATE(AC88,"-",AE88) -> 05-87 | AE88: =IF(AB88=AB87,1+AE87,1) -> 87 | AF88: SABANETA | AG88: 631 | AI88: 87 | AJ88: =CONCATENATE($AA$1,"-",AI88) -> -87 | AK88: =IFERROR(VLOOKUP(AJ88,$AD$2:$AG$1120,3,0),"") | AL88: =IFERROR(VLOOKUP(AJ88,$AD$2:$AG$1120,4,0),"") | AS88: 1521 | AT88: 101 | AU88: Fabricación de calzado de cuero y piel, con cualquier tipo de suela | AV88: 4.14 | AX88: 1394 | AY88: Fabricación de cuerdas, cordeles, cables, bramantes y redes. | BA88: EMPRESAS DEDICADAS AL COMERCIO AL POR MAYOR DE FIBRAS TEXTILES | BB88: 1515401
T89: GROENLANDIA | U89: 305 | AB89: Antioquia | AC89: 05 | AD89: =CONCATENATE(AC89,"-",AE89) -> 05-88 | AE89: =IF(AB89=AB88,1+AE88,1) -> 88 | AF89: SALGAR | AG89: 642 | AI89: 88 | AJ89: =CONCATENATE($AA$1,"-",AI89) -> -88 | AK89: =IFERROR(VLOOKUP(AJ89,$AD$2:$AG$1120,3,0),"") | AL89: =IFERROR(VLOOKUP(AJ89,$AD$2:$AG$1120,4,0),"") | AS89: 1522 | AT89: 101 | AU89: Fabricación de otros tipos de calzado, excepto calzado de cuero y piel | AV89: 4.14 | AX89: 1399 | AY89: Fabricación de otros artículos textiles n.c.p. | BA89: EMPRESAS DEDICADAS AL COMERCIO AL POR MAYOR DE OTROS PRODUCTOS INTERMEDIOS NCP | BB89: 1515901
T90: GUADALUPE | U90: 309 | AB90: Antioquia | AC90: 05 | AD90: =CONCATENATE(AC90,"-",AE90) -> 05-89 | AE90: =IF(AB90=AB89,1+AE89,1) -> 89 | AF90: SAN ANDRÉS | AG90: 647 | AI90: 89 | AJ90: =CONCATENATE($AA$1,"-",AI90) -> -89 | AK90: =IFERROR(VLOOKUP(AJ90,$AD$2:$AG$1120,3,0),"") | AL90: =IFERROR(VLOOKUP(AJ90,$AD$2:$AG$1120,4,0),"") | AS90: 1523 | AT90: 103 | AU90: Fabricación de partes del calzado | AV90: 11.04 | AX90: 1410 | AY90: Confección de prendas de vestir, excepto prendas de piel. | BA90: EMPRESAS DEDICADAS AL COMERCIO AL POR MAYOR DE MAQUINARIA PARA OFICINA, CONTABILIDAD E INFORMÁTICA. | BB90: 1516301
T91: GUAM | U91: 313 | AB91: Antioquia | AC91: 05 | AD91: =CONCATENATE(AC91,"-",AE91) -> 05-90 | AE91: =IF(AB91=AB90,1+AE90,1) -> 90 | AF91: SAN CARLOS | AG91: 649 | AI91: 90 | AJ91: =CONCATENATE($AA$1,"-",AI91) -> -90 | AK91: =IFERROR(VLOOKUP(AJ91,$AD$2:$AG$1120,3,0),"") | AL91: =IFERROR(VLOOKUP(AJ91,$AD$2:$AG$1120,4,0),"") | AS91: 1610 | AT91: 103 | AU91: Aserrado, acepillado e impregnación de la madera | AV91: 11.04 | AX91: 1420 | AY91: Fabricación de artículos de piel. | BA91: EMPRESAS DEDICADAS AL COMERCIO AL POR MENOR, EN ESTABLECIMIENTOS NO ESPECIALIZADOS, CON SURTIDO COMPUESTO PRINCIPALMENTE DE ALIMENTOS (VÍVERES EN GENERAL), BEBIDAS Y TABACO INCLUYE LA VENTA DE MERCANCÍAS | BB91: 1521101
T92: GUATEMALA | U92: 317 | AB92: Antioquia | AC92: 05 | AD92: =CONCATENATE(AC92,"-",AE92) -> 05-91 | AE92: =IF(AB92=AB91,1+AE91,1) -> 91 | AF92: SAN FRANCISCO | AG92: 652 | AI92: 91 | AJ92: =CONCATENATE($AA$1,"-",AI92) -> -91 | AK92: =IFERROR(VLOOKUP(AJ92,$AD$2:$AG$1120,3,0),"") | AL92: =IFERROR(VLOOKUP(AJ92,$AD$2:$AG$1120,4,0),"") | AS92: 1620 | AT92: 103 | AU92: Fabricación de hojas de madera para enchapado; fabricación de tableros contrachapados, tableros laminados, tableros de partículas y otros tableros y paneles | AV92: 11.04 | AX92: 1430 | AY92: Fabricación de artículos de punto y ganchillo. | BA92: EMPRESAS DEDICADAS AL COMERCIO AL POR MENOR EN ESTABLECIMIENTOS NO ESPECIALIZADOS CON SURTIDO COMPUESTO PRINCIPALMENTE POR PRODUCTOS DIFERENTES DE ALIMENTOS (VÍVERES EN GENERAL), BEBIDAS Y TABACOS HACE REFERENCIA A EMPRESAS DEDICADAS A LA VENTA AL MENUDEO EN MISCELÁNEAS | BB92: 1521901
T93: GUAYANA FRANCESA | U93: 325 | AB93: Antioquia | AC93: 05 | AD93: =CONCATENATE(AC93,"-",AE93) -> 05-92 | AE93: =IF(AB93=AB92,1+AE92,1) -> 92 | AF93: SAN JERÓNIMO | AG93: 656 | AI93: 92 | AJ93: =CONCATENATE($AA$1,"-",AI93) -> -92 | AK93: =IFERROR(VLOOKUP(AJ93,$AD$2:$AG$1120,3,0),"") | AL93: =IFERROR(VLOOKUP(AJ93,$AD$2:$AG$1120,4,0),"") | AS93: 1630 | AT93: 103 | AU93: Fabricación de partes y piezas de madera, de carpintería y ebanistería para la construcción y para edificios | AV93: 11.04 | AX93: 1511 | AY93: Curtido y recurtido de cueros; recurtido y teñido de pieles. | BA93: EMPRESAS DEDICADAS AL COMERCIO AL POR MENOR DE FRUTAS Y VERDURAS, EN ESTABLECIMIENTOS ESPECIALIZADOS | BB93: 1522101
T94: GUINEA | U94: 329 | AB94: Antioquia | AC94: 05 | AD94: =CONCATENATE(AC94,"-",AE94) -> 05-93 | AE94: =IF(AB94=AB93,1+AE93,1) -> 93 | AF94: SAN JOSÉ DE LA MONTAÑA | AG94: 658 | AI94: 93 | AJ94: =CONCATENATE($AA$1,"-",AI94) -> -93 | AK94: =IFERROR(VLOOKUP(AJ94,$AD$2:$AG$1120,3,0),"") | AL94: =IFERROR(VLOOKUP(AJ94,$AD$2:$AG$1120,4,0),"") | AS94: 1640 | AT94: 103 | AU94: Fabricación de recipientes de madera | AV94: 11.04 | AX94: 1512 | AY94: Fabricación de artículos de viaje, bolsos de mano y artículos similares elaborados en cuero, y fabricación de artículos de talabartería y guarnicionería. | BA94: EMPRESAS DEDICADAS AL COMERCIO AL POR MENOR DE LECHE, PRODUCTOS LÁCTEOS Y HUEVOS EN ESTABLECIMIENTOS ESPECIALIZADOS INCLUYE LA VENTA SIN AUTO TRANSPORTE DE LECHE | BB94: 1522201
... T126: LIBERIA | U126: 434 | AB126: Antioquia | AC126: 05 | AD126: =CONCATENATE(AC126,"-",AE126) -> 05-125 | AE126: =IF(AB126=AB125,1+AE125,1) -> 125 | AF126: ZARAGOZA | AG126: 895 | AI126: 125 | AJ126: =CONCATENATE($AA$1,"-",AI126) -> -125 | AK126: =IFERROR(VLOOKUP(AJ126,$AD$2:$AG$1120,3,0),"") | AL126: =IFERROR(VLOOKUP(AJ126,$AD$2:$AG$1120,4,0),"") | AS126: 2396 | AT126: 103 | AU126: Corte, tallado y acabado de la piedra | AV126: 11.04 | AX126: 2221 | AY126: Fabricación de formas básicas de plástico. | BA126: Actividades de consultoria informatica y actividades de administracion de instalaciones informaticas, incluye los servicios de consultoria para sistemas de ingenieria y fabricacion asistida por computador y analisis de requerimientos para la instalacion de equipos informaticos, la planificacion y el diseño de los sistemas informaticos que integran el equipo (hardware), programas informaticos (software) y tecnologias de las comunicaciones (incluye redes de area local [LAN], red de area extensa [WAN], entre otras) | BB126: 1620202
T127: LIBIA(INCLUYE FEZZAN | U127: 438 | AB127: Atlántico | AC127: 08 | AD127: =CONCATENATE(AC127,"-",AE127) -> 08-1 | AE127: =IF(AB127=AB126,1+AE126,1) -> 1 | AF127: BARRANQUILLA | AG127: 001 | AK127: =IFERROR(VLOOKUP(AJ3,$M$10:$P$1128,3,0),"") | AS127: 2399 | AT127: 103 | AU127: Fabricación de otros productos minerales no metálicos n.c.p. | AV127: 11.04 | AX127: 2229 | AY127: Fabricación de artículos de plástico n.c.p. | BA127: Otras actividades de las tecnologias de informacion y las actividades relacionadas con informatica no clasificadas en otras partes, incluye la recuperacion de la informacion de los ordenadores en casos de desastre informatico, configuracion, instalacion de software o programas informaticos. | BB127: 1620901
T128: LIECHTENSTEIN | U128: 440 | AB128: Atlántico | AC128: 08 | AD128: =CONCATENATE(AC128,"-",AE128) -> 08-2 | AE128: =IF(AB128=AB127,1+AE127,1) -> 2 | AF128: BARANOA | AG128: 078 | AK128: =IFERROR(VLOOKUP(AJ4,$M$10:$P$1128,3,0),"") | AS128: 2410 | AT128: 102 | AU128: Industrias básicas de hierro y de acero | AV128: 6.9 | AX128: 2310 | AY128: Fabricación de vidrio y productos de vidrio. | BA128: Procesamiento de datos, alojamiento (hosting) y actividades relacionadas, incluye suministro de infraestructura para servicios de hosting, servicios de procesamiento de datos y actividades conexas relacionadas, alojamiento de sitios web, servicios de transmision de secuencias de video por internet (streaming), aplicaciones, suministro a los clientes de acceso en tiempo compartido a servicios centrales | BB128: 1631101
T129: LITUANIA | U129: 443 | AB129: Atlántico | AC129: 08 | AD129: =CONCATENATE(AC129,"-",AE129) -> 08-3 | AE129: =IF(AB129=AB128,1+AE128,1) -> 3 | AF129: CAMPO DE LA CRUZ | AG129: 137 | AK129: =IFERROR(VLOOKUP(AJ5,$M$10:$P$1128,3,0),"") | AS129: 2421 | AT129: 103 | AU129: Industrias básicas de metales preciosos | AV129: 11.04 | AX129: 2391 | AY129: Fabricación de productos refractarios. | BA129: Procesamiento de datos, alojamiento (hosting) y actividades relacionadas, incluye el funcionamiento de oficinas de servicio de informatica dedicadas al procesamiento de datos y alojamiento web, el suministro de servicio de registro, tabulacion, digitacion de datos, escaneo optico de datos y de documentos | BB129: 1631102
T130: LUXEMBURGO | U130: 445 | AB130: Atlántico | AC130: 08 | AD130: =CONCATENATE(AC130,"-",AE130) -> 08-4 | AE130: =IF(AB130=AB129,1+AE129,1) -> 4 | AF130: CANDELARIA | AG130: 141 | AK130: =IFERROR(VLOOKUP(AJ6,$M$10:$P$1128,3,0),"") | AS130: 2429 | AT130: 103 | AU130: Industrias básicas de otros metales no ferrosos | AV130: 11.04 | AX130: 2392 | AY130: Fabricación de materiales de arcilla para la construcción. | BA130: Portales web, incluye la explotacion de los sitios web para generar y mantener extensas bases de datos y de contenido en un formato de facil busqueda, portales de internet y que funcionan como portales de internet, tales como sitios de medios de difusion que proporcionan los contenidos que se actualizan de forma periodica. | BB130: 1631201
T131: MACAO | U131: 447 | AB131: Atlántico | AC131: 08 | AD131: =CONCATENATE(AC131,"-",AE131) -> 08-5 | AE131: =IF(AB131=AB130,1+AE130,1) -> 5 | AF131: GALAPA | AG131: 296 | AK131: =IFERROR(VLOOKUP(AJ7,$M$10:$P$1128,3,0),"") | AS131: 2431 | AT131: 102 | AU131: Fundición de hierro y de acero | AV131: 6.9 | AX131: 2393 | AY131: Fabricación de otros productos de cerámica y porcelana. | BA131: EMPRESAS DEDICADAS A ACTIVIDADES DE AGENCIAS DE VIAJES Y ORGANIZADORES DE VIAJES; INCLUYE ASISTENCIA A TURISTAS NCP | BB131: 1634001
...
